Sam/sd_parser/src/header_finder.sv
`timescale 1ns / 1ps
`default_nettype none


/*
STATUS: WORKING
  tested a few different ways given the 4 bytes are inputted consecutively. right now there is nothing to reset
  the internal header_byte_counter, so if it stops getting the bytes in halfway, but no rst signal is sent in,
  this shit will output data at the wrong time.
  dont know how to fix this realistically, unless we take the byte_counter as an input.
  but that method is not really sustainable for downstream stuff (cus of the CRC16 check throwing the byte count off)
  so i don't want to make that counter into some kind of global system.
  I would rather just ensure that the entire frame is loaded (ti doesn't quite reading in the frame halfway).
  If that system breaks, we have the reset button to save the system.
*/

module header_finder(
    input wire clk,
    input wire rst,
    input wire [7:0] axiid,
    input wire axiiv,

    output logic valid_header,
    output logic prot,
    output logic [1:0] mode,
    output logic [1:0] mode_ext,
    output logic [1:0] emphasis,
    output logic [10:0] frame_size
);

    logic [11:0] sync;
    logic version;
    logic [1:0] layer;
    logic [15:0] samp_rate;
    logic [31:0] header;
    logic padding;
    logic [8:0] bitrate;

    always_comb begin
      if ((sync == 12'd4095) && (version) && (samp_rate == 2'b00) && (bitrate > 0)) valid_header = 1;
      else valid_header = 0;
    end

    always_ff @(posedge clk) begin
        if (rst) begin
          header <= 0;
        end else begin
            if (axiiv) begin
              header <= {header[23:0], axiid};
            end
        end
    end

    always_comb begin
        case(header[15:12])
            4'b0001 : bitrate = 9'd32;
            4'b0010 : bitrate = 9'd40;
            4'b0011 : bitrate = 9'd48;
            4'b0100 : bitrate = 9'd56;
            4'b0101 : bitrate = 9'd64;
            4'b0110 : bitrate = 9'd80;
            4'b0111 : bitrate = 9'd96;
            4'b1000 : bitrate = 9'd112;
            4'b1001 : bitrate = 9'd128;
            4'b1010 : bitrate = 9'd160;
            4'b1011 : bitrate = 9'd192;
            4'b1100 : bitrate = 9'd224;
            4'b1101 : bitrate = 9'd256;
            4'b1110 : bitrate = 9'd320;
            default : bitrate = 9'd0;
        endcase
    end

    assign version = header[19];
    assign layer = header[18:17];
    assign samp_rate = header[11:10];
    assign sync = header[31:20];
    assign prot = header[16];
    assign padding = header[9];
    assign mode = header[7:6];
    assign mode_ext = header[5:4];
    assign emphasis = header[1:0];

    //compute the frame size according to a look up table (so we dont have to divide by 44100):
    //note that this HAS to be done within a clock cycle because the frame parsing takes this information into account
    always_comb begin
      case(bitrate)
          9'd32   :   frame_size = padding ? (11'd104  + 1) : (11'd104) ;
          9'd40   :   frame_size = padding ? (11'd130  + 1) : (11'd130) ;
          9'd48   :   frame_size = padding ? (11'd156  + 1) : (11'd156) ;
          9'd56   :   frame_size = padding ? (11'd182  + 1) : (11'd182) ;
          9'd64   :   frame_size = padding ? (11'd208  + 1) : (11'd208) ;
          9'd80   :   frame_size = padding ? (11'd261  + 1) : (11'd261) ;
          9'd96   :   frame_size = padding ? (11'd313  + 1) : (11'd313) ;
          9'd112  :   frame_size = padding ? (11'd365  + 1) : (11'd365) ;
          9'd128  :   frame_size = padding ? (11'd417  + 1) : (11'd417) ;
          9'd160  :   frame_size = padding ? (11'd522  + 1) : (11'd522) ;
          9'd192  :   frame_size = padding ? (11'd626  + 1) : (11'd626) ;
          9'd224  :   frame_size = padding ? (11'd731  + 1) : (11'd731) ;
          9'd256  :   frame_size = padding ? (11'd835  + 1) : (11'd835) ;
          9'd320  :   frame_size = padding ? (11'd1044 + 1) : (11'd1044);
          default :   frame_size = 9'd0;
      endcase

    end

    //frame size cases compared to bitrate cases:
    /*
    bitrates    -> [0,  32,  40,  48,  56,  64,  80,  96, 112, 128, 160, 192, 224, 256,  320, 0]
    frame sizes -> [0, 104, 130, 156, 182, 208, 261, 313, 365, 417, 522, 626, 731, 835, 1044, 0]
    */
    //note that this LUT is only possible by assuming the MPEG-1 Layer III 44.1kHz stuff too.
endmodule

`default_nettype wire

Alex/test_builds/parser_v2/sim/header_finder_tb.sv
`default_nettype none
`timescale 1ns / 1ps

module header_tb;

  logic clk;
  logic rst;
  logic [7:0] axiid;
  logic axiiv;

  logic valid_header;
  logic prot;
  logic [1:0] mode;
  logic [1:0] mode_ext;
  logic [1:0] emphasis;
  logic [10:0] frame_size;

  logic [31:0] header_code;
  logic [39:0] header_code_2;

  header_finder uut (
      .clk(clk),
      .rst(rst),
      .axiid(axiid),
      .axiiv(axiiv),
      .valid_header(valid_header),
      .prot(prot),
      .mode(mode),
      .mode_ext(mode_ext),
      .emphasis(emphasis),
      .frame_size(frame_size)
    );

  always begin
    #10;
    clk = !clk;     //clock cycles now happend every 20!
  end

  initial begin
    $dumpfile("sim/header_finder_sim.vcd");
    $dumpvars(0, header_tb);
    $display("Starting Sim");

    header_code = 32'b1111_1111_1111_1011_1001_0010_0110_0100;

    clk = 0;
    rst = 0;

    axiiv = 0;
    axiid = 0;    //make the inputs 0 too!
    #20;
    rst = 1;
    #20;
    rst = 0;

    //TRANSMIT DESTINATION

    for (int i = 31; i > 0; i -= 8) begin
      axiiv = 1;
      axiid = header_code[i-:8];
      #20;

      axiiv = 0;
      #100;
    end

    header_code_2 = 40'b1100_1111_1111_1111_1111_1011_1001_0010_0110_0100;

    #200
    for (int j = 39; j > 0; j -= 8) begin
      axiiv = 1;
      axiid = header_code_2[j-:8];
      #20;

      axiiv = 0;
      #100;
    end


    $display("Finishing Sim");
    $finish;

  end

endmodule


`default_nettype wire

Sam/sd_parser/sim/header_finder_sim.vcd
$date
	Sat Dec 03 22:56:16 2022
$end
$version
	Icarus Verilog
$end
$timescale
	1ps
$end
$scope module header_tb $end
$var wire 1 ! valid_header $end
$var wire 1 " prot $end
$var wire 2 # mode_ext [1:0] $end
$var wire 2 $ mode [1:0] $end
$var wire 11 % frame_size [10:0] $end
$var wire 2 & emphasis [1:0] $end
$var reg 8 ' axiid [7:0] $end
$var reg 1 ( axiiv $end
$var reg 1 ) clk $end
$var reg 32 * header_code [31:0] $end
$var reg 40 + header_code_2 [39:0] $end
$var reg 1 , rst $end
$scope module uut $end
$var wire 8 - axiid [7:0] $end
$var wire 1 ( axiiv $end
$var wire 1 ) clk $end
$var wire 1 , rst $end
$var wire 1 . version $end
$var wire 12 / sync [11:0] $end
$var wire 16 0 samp_rate [15:0] $end
$var wire 1 " prot $end
$var wire 1 1 padding $end
$var wire 2 2 mode_ext [1:0] $end
$var wire 2 3 mode [1:0] $end
$var wire 2 4 layer [1:0] $end
$var wire 2 5 emphasis [1:0] $end
$var reg 9 6 bitrate [8:0] $end
$var reg 11 7 frame_size [10:0] $end
$var reg 32 8 header [31:0] $end
$var reg 1 ! valid_header $end
$upscope $end
$scope begin $ivl_for_loop0 $end
$var integer 32 9 i [31:0] $end
$upscope $end
$scope begin $ivl_for_loop1 $end
$var integer 32 : j [31:0] $end
$upscope $end
$upscope $end
$enddefinitions $end
$comment Show the parameter values. $end
$dumpall
$end
#0
$dumpvars
b0 :
b0 9
bx 8
b0 7
b0 6
bx 5
bx 4
bx 3
bx 2
x1
b0xx 0
bx /
x.
b0 -
0,
bx +
b11111111111110111001001001100100 *
0)
0(
b0 '
bx &
b0 %
bx $
bx #
x"
0!
$end
#10000
1)
#20000
0)
1,
#30000
0.
b0 4
b0 0
b0 /
0"
01
b0 $
b0 3
b0 #
b0 2
b0 &
b0 5
b0 8
1)
#40000
0)
b11111111 '
b11111111 -
1(
b11111 9
0,
#50000
b11 $
b11 3
b11 #
b11 2
b11 &
b11 5
b11111111 8
1)
#60000
0)
0(
#70000
1)
#80000
0)
#90000
1)
#100000
0)
#110000
1)
#120000
0)
#130000
1)
#140000
0)
#150000
1)
#160000
0)
b11111011 '
b11111011 -
1(
b10111 9
#170000
b11 0
11
b1111111111111011 8
1)
#180000
0)
0(
#190000
1)
#200000
0)
#210000
1)
#220000
0)
#230000
1)
#240000
0)
#250000
1)
#260000
0)
#270000
1)
#280000
0)
b10010010 '
b10010010 -
1(
b1111 9
#290000
1.
b11 4
b10 0
b1111 /
1"
b10 $
b10 3
b1 #
b1 2
b10 &
b10 5
b111111111111101110010010 8
1)
#300000
0)
0(
#310000
1)
#320000
0)
#330000
1)
#340000
0)
#350000
1)
#360000
0)
#370000
1)
#380000
0)
#390000
1)
#400000
0)
b1100100 '
b1100100 -
1(
b111 9
#410000
b110100010 %
b110100010 7
1!
b10000000 6
b1 4
b0 0
b111111111111 /
b1 $
b1 3
b10 #
b10 2
b0 &
b0 5
b11111111111110111001001001100100 8
1)
#420000
0)
0(
#430000
1)
#440000
0)
#450000
1)
#460000
0)
#470000
1)
#480000
0)
#490000
1)
#500000
0)
#510000
1)
#520000
0)
b1100111111111111111110111001001001100100 +
b11111111111111111111111111111111 9
#530000
1)
#540000
0)
#550000
1)
#560000
0)
#570000
1)
#580000
0)
#590000
1)
#600000
0)
#610000
1)
#620000
0)
#630000
1)
#640000
0)
#650000
1)
#660000
0)
#670000
1)
#680000
0)
#690000
1)
#700000
0)
#710000
1)
#720000
0)
b11001111 '
b11001111 -
1(
b100111 :
#730000
0!
b100000101 %
b100000101 7
b1010000 6
0.
b1 0
b111110111001 /
0"
01
b11 $
b11 3
b0 #
b0 2
b11 &
b11 5
b11111011100100100110010011001111 8
1)
#740000
0)
0(
#750000
1)
#760000
0)
#770000
1)
#780000
0)
#790000
1)
#800000
0)
#810000
1)
#820000
0)
#830000
1)
#840000
0)
b11111111 '
b11111111 -
1(
b11111 :
#850000
b1011011100 %
b1011011100 7
b11100000 6
b10 4
b11 0
b100100100110 /
11
b11 #
b11 2
b10010010011001001100111111111111 8
1)
#860000
0)
0(
#870000
1)
#880000
0)
#890000
1)
#900000
0)
#910000
1)
#920000
0)
#930000
1)
#940000
0)
#950000
1)
#960000
0)
b11111011 '
b11111011 -
1(
b10111 :
#970000
b0 %
b0 7
b0 6
1.
b11 4
b11001001100 /
1"
b1100100110011111111111111111011 8
1)
#980000
0)
0(
#990000
1)
#1000000
0)
#1010000
1)
#1020000
0)
#1030000
1)
#1040000
0)
#1050000
1)
#1060000
0)
#1070000
1)
#1080000
0)
b10010010 '
b10010010 -
1(
b1111 :
#1090000
b10 0
b110011111111 /
b10 $
b10 3
b1 #
b1 2
b10 &
b10 5
b11001111111111111111101110010010 8
1)
#1100000
0)
0(
#1110000
1)
#1120000
0)
#1130000
1)
#1140000
0)
#1150000
1)
#1160000
0)
#1170000
1)
#1180000
0)
#1190000
1)
#1200000
0)
b1100100 '
b1100100 -
1(
b111 :
#1210000
b110100010 %
b110100010 7
1!
b10000000 6
b1 4
b0 0
b111111111111 /
b1 $
b1 3
b10 #
b10 2
b0 &
b0 5
b11111111111110111001001001100100 8
1)
#1220000
0)
0(
#1230000
1)
#1240000
0)
#1250000
1)
#1260000
0)
#1270000
1)
#1280000
0)
#1290000
1)
#1300000
0)
#1310000
1)
#1320000
0)
b11111111111111111111111111111111 :
