Alex/test_builds/parser_v2/src/sf_parser.sv
`default_nettype none
`timescale 1ns / 1ps

module sf_parser(
  input wire clk,
  input wire rst,
  input wire axiid,
  input wire axiiv,

  input wire gr,
  input wire [3:0] scalefac_compress,
  input wire window_switching_flag,
  input wire [1:0] block_type,
  input wire mixed_block_flag,
  input wire [3:0] scfsi,
  input wire si_valid,

  output logic [11:0][2:0] scalefac_s,
  output logic [20:0] scalefac_l,
  output logic axiov
  );

    logic bitlen_1, bitlen_2;

    logic [11:0] part2_3_length_save;
    logic [3:0] scalefac_compress_save;
    logic window_switching_flag_save;
    logic [1:0] block_type_save;
    logic mixed_block_flag_save;
    logic [3:0] scfsi_save;
    logic si_valid_save;
    logic gr_save;

    always_comb begin
      case(scalefac_compress_save)
        4'd0    : bitlen_1 = 0;
        4'd1    : bitlen_1 = 0;
        4'd2    : bitlen_1 = 0;
        4'd3    : bitlen_1 = 0;
        4'd4    : bitlen_1 = 3;
        4'd5    : bitlen_1 = 1;
        4'd6    : bitlen_1 = 1;
        4'd7    : bitlen_1 = 1;
        4'd8    : bitlen_1 = 2;
        4'd9    : bitlen_1 = 2;
        4'd10   : bitlen_1 = 2;
        4'd11   : bitlen_1 = 3;
        4'd12   : bitlen_1 = 3;
        4'd13   : bitlen_1 = 3;
        4'd14   : bitlen_1 = 4;
        4'd15   : bitlen_1 = 4;
      endcase
      case(scalefac_compress_save)
        4'd0    : bitlen_2 = 0;
        4'd1    : bitlen_2 = 1;
        4'd2    : bitlen_2 = 2;
        4'd3    : bitlen_2 = 3;
        4'd4    : bitlen_2 = 0;
        4'd5    : bitlen_2 = 1;
        4'd6    : bitlen_2 = 2;
        4'd7    : bitlen_2 = 3;
        4'd8    : bitlen_2 = 1;
        4'd9    : bitlen_2 = 2;
        4'd10   : bitlen_2 = 3;
        4'd11   : bitlen_2 = 1;
        4'd12   : bitlen_2 = 2;
        4'd13   : bitlen_2 = 3;
        4'd14   : bitlen_2 = 2;
        4'd15   : bitlen_2 = 3;
      endcase
    end

    logic [3:0] buffer;   //needs atmost 4 bits at a time.
    logic [31:0] bit_counter;  //idk what the max is. whatever
    logic done;       //cus there is not specific count for when tis finished...

    logic [2:0] shift_1, shift_2;

    assign shift_1 = 3'd4 - bitlen_1;
    assign shift_2 = 3'd4 - bitlen_2;   //these are useful terms for bitshifting

    always_ff @(posedge clk) begin
      if (rst) begin
        scalefac_l <= 0;
        scalefac_s <= 0;
        buffer <= 0;
        bit_counter <= 0;
        axiov <= 0;
      end else begin
        if (si_valid) begin
          scalefac_compress_save <= scalefac_compress;
          window_switching_flag_save <= window_switching_flag;
          block_type_save <= block_type;
          mixed_block_flag_save <= mixed_block_flag;
          scfsi_save <= scfsi;
          gr_save <= gr;

          //also just reset all the other variables for now:
          axiov <= 0;
          bit_counter <= (axiiv) ? 1 : 0;
          buffer <= (axiiv) ? {3'd0, axiid} : 4'd0;    //accommodate getting information along with SI stuff.
          scalefac_l <= 0;
          scalefac_s <= 0;
        end
        else if (axiov) begin
          axiov <= 0;
          bit_counter <= 0;
          buffer <= 0;
          scalefac_l <= 0;
          scalefac_s <= 0;
        end
        else if (axiiv) begin
          buffer <= {buffer[3:0], axiid};
          bit_counter <= bit_counter + 1;
          axiov <= 0;
        end
        else begin

                if (window_switching_flag_save && (block_type_save == 2) && (mixed_block_flag_save)) begin
                      //BRANCH 1:
                      if      (bit_counter == 1 * (bitlen_1)) scalefac_l[0] <= (buffer << shift_1) >> shift_1;
                      else if (bit_counter == 2 * (bitlen_1)) scalefac_l[1] <= (buffer << shift_1) >> shift_1;
                      else if (bit_counter == 3 * (bitlen_1)) scalefac_l[2] <= (buffer << shift_1) >> shift_1;
                      else if (bit_counter == 4 * (bitlen_1)) scalefac_l[3] <= (buffer << shift_1) >> shift_1;
                      else if (bit_counter == 5 * (bitlen_1)) scalefac_l[4] <= (buffer << shift_1) >> shift_1;
                      else if (bit_counter == 6 * (bitlen_1)) scalefac_l[5] <= (buffer << shift_1) >> shift_1;
                      else if (bit_counter == 7 * (bitlen_1)) scalefac_l[6] <= (buffer << shift_1) >> shift_1;
                      else if (bit_counter == 8 * (bitlen_1)) scalefac_l[7] <= (buffer << shift_1) >> shift_1;
                end

                else if (window_switching_flag_save && (block_type_save == 2)) begin
                  //Branch 2:

                      if      (bit_counter == (1 * bitlen_1)) scalefac_s[0][0] <= (buffer << shift_1) >> shift_1;
                      else if (bit_counter == (2 * bitlen_1)) scalefac_s[0][1] <= (buffer << shift_1) >> shift_1;
                      else if (bit_counter == (3 * bitlen_1)) scalefac_s[0][2] <= (buffer << shift_1) >> shift_1;
                      else if (bit_counter == (4 * bitlen_1)) scalefac_s[1][0] <= (buffer << shift_1) >> shift_1;
                      else if (bit_counter == (5 * bitlen_1)) scalefac_s[1][1] <= (buffer << shift_1) >> shift_1;
                      else if (bit_counter == (6 * bitlen_1)) scalefac_s[1][2] <= (buffer << shift_1) >> shift_1;
                      else if (bit_counter == (7 * bitlen_1)) scalefac_s[2][0] <= (buffer << shift_1) >> shift_1;
                      else if (bit_counter == (8 * bitlen_1)) scalefac_s[2][1] <= (buffer << shift_1) >> shift_1;
                      else if (bit_counter == (9 * bitlen_1)) scalefac_s[2][2] <= (buffer << shift_1) >> shift_1;
                      else if (bit_counter == (10 * bitlen_1)) scalefac_s[3][0] <= (buffer << shift_1) >> shift_1;
                      else if (bit_counter == (11 * bitlen_1)) scalefac_s[3][1] <= (buffer << shift_1) >> shift_1;
                      else if (bit_counter == (12 * bitlen_1)) scalefac_s[3][2] <= (buffer << shift_1) >> shift_1;
                      else if (bit_counter == (13 * bitlen_1)) scalefac_s[4][0] <= (buffer << shift_1) >> shift_1;
                      else if (bit_counter == (14 * bitlen_1)) scalefac_s[4][1] <= (buffer << shift_1) >> shift_1;
                      else if (bit_counter == (15 * bitlen_1)) scalefac_s[4][2] <= (buffer << shift_1) >> shift_1;
                      else if (bit_counter == (16 * bitlen_1)) scalefac_s[5][0] <= (buffer << shift_1) >> shift_1;
                      else if (bit_counter == (17 * bitlen_1)) scalefac_s[5][1] <= (buffer << shift_1) >> shift_1;
                      else if (bit_counter == (18 * bitlen_1)) scalefac_s[5][2] <= (buffer << shift_1) >> shift_1;

                      else if (bit_counter == (18 * bitlen_1 + 1  * bitlen_2)) scalefac_s[6 ][0] <= (buffer << shift_2) >> shift_2;
                      else if (bit_counter == (18 * bitlen_1 + 2  * bitlen_2)) scalefac_s[6 ][1] <= (buffer << shift_2) >> shift_2;
                      else if (bit_counter == (18 * bitlen_1 + 3  * bitlen_2)) scalefac_s[6 ][2] <= (buffer << shift_2) >> shift_2;
                      else if (bit_counter == (18 * bitlen_1 + 4  * bitlen_2)) scalefac_s[7 ][0] <= (buffer << shift_2) >> shift_2;
                      else if (bit_counter == (18 * bitlen_1 + 5  * bitlen_2)) scalefac_s[7 ][1] <= (buffer << shift_2) >> shift_2;
                      else if (bit_counter == (18 * bitlen_1 + 6  * bitlen_2)) scalefac_s[7 ][2] <= (buffer << shift_2) >> shift_2;
                      else if (bit_counter == (18 * bitlen_1 + 7  * bitlen_2)) scalefac_s[8 ][0] <= (buffer << shift_2) >> shift_2;
                      else if (bit_counter == (18 * bitlen_1 + 8  * bitlen_2)) scalefac_s[8 ][1] <= (buffer << shift_2) >> shift_2;
                      else if (bit_counter == (18 * bitlen_1 + 9  * bitlen_2)) scalefac_s[8 ][2] <= (buffer << shift_2) >> shift_2;
                      else if (bit_counter == (18 * bitlen_1 + 10 * bitlen_2)) scalefac_s[9 ][0] <= (buffer << shift_2) >> shift_2;
                      else if (bit_counter == (18 * bitlen_1 + 11 * bitlen_2)) scalefac_s[9 ][1] <= (buffer << shift_2) >> shift_2;
                      else if (bit_counter == (18 * bitlen_1 + 12 * bitlen_2)) scalefac_s[9 ][2] <= (buffer << shift_2) >> shift_2;
                      else if (bit_counter == (18 * bitlen_1 + 13 * bitlen_2)) scalefac_s[10][0] <= (buffer << shift_2) >> shift_2;
                      else if (bit_counter == (18 * bitlen_1 + 14 * bitlen_2)) scalefac_s[10][1] <= (buffer << shift_2) >> shift_2;
                      else if (bit_counter == (18 * bitlen_1 + 15 * bitlen_2)) scalefac_s[10][2] <= (buffer << shift_2) >> shift_2;
                      else if (bit_counter == (18 * bitlen_1 + 16 * bitlen_2)) scalefac_s[11][0] <= (buffer << shift_2) >> shift_2;
                      else if (bit_counter == (18 * bitlen_1 + 17 * bitlen_2)) scalefac_s[11][1] <= (buffer << shift_2) >> shift_2;
                      else if (bit_counter == (18 * bitlen_1 + 18 * bitlen_2)) begin
                        scalefac_s[11][2] <= (buffer << shift_2) >> shift_2;
                        axiov <= 1;
                      end

                end

                else begin
                  //the default window. dont worry about copying over teh scalefactors when the gr == 1 here. do that upstream
                  if ((~gr_save) || ~scfsi_save[0]) begin
                    if      (bit_counter == 1 * (bitlen_1)) scalefac_l[0] <= (buffer << shift_1) >> shift_1;
                    else if (bit_counter == 2 * (bitlen_1)) scalefac_l[1] <= (buffer << shift_1) >> shift_1;
                    else if (bit_counter == 3 * (bitlen_1)) scalefac_l[2] <= (buffer << shift_1) >> shift_1;
                    else if (bit_counter == 4 * (bitlen_1)) scalefac_l[3] <= (buffer << shift_1) >> shift_1;
                    else if (bit_counter == 5 * (bitlen_1)) scalefac_l[4] <= (buffer << shift_1) >> shift_1;
                    else if (bit_counter == 6 * (bitlen_1)) scalefac_l[5] <= (buffer << shift_1) >> shift_1;
                  end

                  if (~gr_save || ~scfsi_save[1]) begin
                    if      (bit_counter == 7 * (bitlen_1)) scalefac_l[6]  <= (buffer << shift_1) >> shift_1;
                    else if (bit_counter == 8 * (bitlen_1)) scalefac_l[7]  <= (buffer << shift_1) >> shift_1;
                    else if (bit_counter == 9 * (bitlen_1)) scalefac_l[8]  <= (buffer << shift_1) >> shift_1;
                    else if (bit_counter == 10 * (bitlen_1)) scalefac_l[9]  <= (buffer << shift_1) >> shift_1;
                    else if (bit_counter == 11 * (bitlen_1)) scalefac_l[10] <= (buffer << shift_1) >> shift_1;
                  end

                  if (~gr_save || ~scfsi_save[2]) begin
                    if      (bit_counter == (11 * bitlen_1) + (1 * bitlen_2)) scalefac_l[11]  <= (buffer << shift_1) >> shift_1;
                    else if (bit_counter == (11 * bitlen_1) + (2 * bitlen_2)) scalefac_l[12]  <= (buffer << shift_1) >> shift_1;
                    else if (bit_counter == (11 * bitlen_1) + (3 * bitlen_2)) scalefac_l[13]  <= (buffer << shift_1) >> shift_1;
                    else if (bit_counter == (11 * bitlen_1) + (4 * bitlen_2)) scalefac_l[14]  <= (buffer << shift_1) >> shift_1;
                    else if (bit_counter == (11 * bitlen_1) + (5 * bitlen_2)) scalefac_l[15]  <= (buffer << shift_1) >> shift_1;
                  end

                  if (~gr_save || ~scfsi_save[3]) begin
                    if      (bit_counter == (11 * bitlen_1) + 6 *  (bitlen_2)) scalefac_l[16]  <= (buffer << shift_2) >> shift_2;
                    else if (bit_counter == (11 * bitlen_1) + 7 *  (bitlen_2)) scalefac_l[17]  <= (buffer << shift_2) >> shift_2;
                    else if (bit_counter == (11 * bitlen_1) + 8 *  (bitlen_2)) scalefac_l[18]  <= (buffer << shift_2) >> shift_2;
                    else if (bit_counter == (11 * bitlen_1) + 9 *  (bitlen_2)) scalefac_l[19]  <= (buffer << shift_2) >> shift_2;
                    else if (bit_counter == (11 * bitlen_1) + 10 * (bitlen_2)) begin
                      scalefac_l[20]  <= (buffer << shift_2) >> shift_2;
                      axiov <= 1;
                    end
                  end



                end




        end
      end
    end

endmodule

`default_nettype wire

Alex/test_builds/parser_v2/sim/sf_parser_tb.sv
`default_nettype none
`timescale 1ns / 1ps

module sf_parser_tb;

logic clk;
logic rst;

logic [1037:0] bit_code;

logic gr;
logic [11:0] part2_3_length;
logic [3:0] scalefac_compress;
logic window_switching_flag;
logic [1:0] block_type;
logic mixed_block_flag;
logic [3:0] scfsi;
logic si_valid;

logic [11:0][2:0] scalefac_s;
logic [20:0] scalefac_l;
logic axiov;

logic axiid, axiiv;


sf_parser UUT (
    .clk(clk),
    .rst(rst),
    .axiid(axiid),
    .axiiv(axiiv),
    .gr(gr),
    .scalefac_compress(scalefac_compress),
    .window_switching_flag(window_switching_flag),
    .block_type(block_type),
    .mixed_block_flag(mixed_block_flag),
    .scfsi(scfsi),
    .si_valid(si_valid),
    .scalefac_s(scalefac_s),
    .scalefac_l(scalefac_l),
    .axiov(axiov)
  );

//////////////////////////////////////////

  always begin
    #10;
    clk = !clk;     //clock cycles now happend every 20!
  end

  initial begin
    $dumpfile("sim/sf_parser_sim.vcd");
    $dumpvars(0, sf_parser_tb);
    $display("Starting Sim");

    bit_code = 1038'b010100100000000000001001100011100110011000100110000111011111000101100001110010111011100111001111011001011000111000011100010010011110000001101010000100100001100101001011011100111000101101001011101000111100111111111011100010000010000001000000010001000001011000010110110011010000000111100000000000010001001000100000000101000011000001011000011010000111100001000001000110001100001001010001100011100001111000101101010010011001101101001010001000000000111101011101100011101000100001010110011000100001000111100010101000101010111011100110001000110110110010011010101110101011011001001010000110101100001001000110100000011100001111001001010000010110001011000101100010101000010111110110101110011011011111101111100010011010101010100001100010101010111001001101010100110111011101111111010010110101001101101010110110001110000111110000111101010111110001011100010001101001000100110100100111101101001111010111000100111101011100010111011101111111110100010011101010111111110111001101011111001111000010010101111001001110010001010010110000100110001101110111001011;

    gr = 0;
    mixed_block_flag = 0;
    scalefac_compress = 5;
    window_switching_flag = 1;
    block_type = 3;
    scfsi = 0;
    si_valid = 0;
    axiiv = 0;
    axiid = 0;

    rst = 0;
    clk = 0;
    #20;
    rst = 1;
    #20;
    rst = 0;
    #20;
    si_valid = 1;
    #20;
    si_valid = 0;
    for (int i = 1037; i > 0; i --) begin
      axiid = bit_code[i];
      axiiv = 1;
      #20;
      axiiv = 0;
      #80;
    end


    $display("Finishing Sim");
    $finish;

  end

endmodule


`default_nettype wire

Alex/test_builds/parser_v2/sim/sf_parser_sim.vcd
$date
	Sun Dec 04 12:15:44 2022
$end
$version
	Icarus Verilog
$end
$timescale
	1ps
$end
$scope module sf_parser_tb $end
$var wire 36 ! scalefac_s [35:0] $end
$var wire 21 " scalefac_l [20:0] $end
$var wire 1 # axiov $end
$var reg 1 $ axiid $end
$var reg 1 % axiiv $end
$var reg 1038 & bit_code [1037:0] $end
$var reg 2 ' block_type [1:0] $end
$var reg 1 ( clk $end
$var reg 1 ) gr $end
$var reg 1 * mixed_block_flag $end
$var reg 1 + rst $end
$var reg 4 , scalefac_compress [3:0] $end
$var reg 4 - scfsi [3:0] $end
$var reg 1 . si_valid $end
$var reg 1 / window_switching_flag $end
$scope module UUT $end
$var wire 1 $ axiid $end
$var wire 1 % axiiv $end
$var wire 2 0 block_type [1:0] $end
$var wire 1 ( clk $end
$var wire 1 ) gr $end
$var wire 1 * mixed_block_flag $end
$var wire 1 + rst $end
$var wire 4 1 scalefac_compress [3:0] $end
$var wire 4 2 scfsi [3:0] $end
$var wire 1 . si_valid $end
$var wire 1 / window_switching_flag $end
$var wire 3 3 shift_2 [2:0] $end
$var wire 3 4 shift_1 [2:0] $end
$var reg 1 # axiov $end
$var reg 32 5 bit_counter [31:0] $end
$var reg 1 6 bitlen_1 $end
$var reg 1 7 bitlen_2 $end
$var reg 2 8 block_type_save [1:0] $end
$var reg 4 9 buffer [3:0] $end
$var reg 1 : gr_save $end
$var reg 1 ; mixed_block_flag_save $end
$var reg 4 < scalefac_compress_save [3:0] $end
$var reg 21 = scalefac_l [20:0] $end
$var reg 36 > scalefac_s [35:0] $end
$var reg 4 ? scfsi_save [3:0] $end
$var reg 1 @ window_switching_flag_save $end
$upscope $end
$scope begin $ivl_for_loop0 $end
$var integer 32 A i [31:0] $end
$upscope $end
$upscope $end
$enddefinitions $end
$comment Show the parameter values. $end
$dumpall
$end
#0
$dumpvars
b0 A
x@
bx ?
bx >
bx =
bx <
x;
x:
bx 9
bx 8
x7
x6
bx 5
bx 4
bx 3
b0 2
b101 1
b11 0
1/
0.
b0 -
b101 ,
0+
0*
0)
0(
b11 '
b10100100000000000001001100011100110011000100110000111011111000101100001110010111011100111001111011001011000111000011100010010011110000001101010000100100001100101001011011100111000101101001011101000111100111111111011100010000010000001000000010001000001011000010110110011010000000111100000000000010001001000100000000101000011000001011000011010000111100001000001000110001100001001010001100011100001111000101101010010011001101101001010001000000000111101011101100011101000100001010110011000100001000111100010101000101010111011100110001000110110110010011010101110101011011001001010000110101100001001000110100000011100001111001001010000010110001011000101100010101000010111110110101110011011011111101111100010011010101010100001100010101010111001001101010100110111011101111111010010110101001101101010110110001110000111110000111101010111110001011100010001101001000100110100100111101101001111010111000100111101011100010111011101111111110100010011101010111111110111001101011111001111000010010101111001001110010001010010110000100110001101110111001011 &
0%
0$
x#
bx "
bx !
$end
#10000
1(
#20000
0(
1+
#30000
0#
b0 5
b0 9
b0 !
b0 >
b0 "
b0 =
1(
#40000
0(
0+
#50000
1(
#60000
0(
1.
#70000
b11 3
17
b11 4
16
0:
b0 ?
0;
b11 8
1@
b101 <
1(
#80000
0(
1%
b10000001101 A
0.
#90000
b1 5
1(
#100000
0(
0%
#110000
1(
#120000
0(
#130000
1(
#140000
0(
#150000
1(
#160000
0(
#170000
1(
#180000
0(
1%
1$
b10000001100 A
#190000
b10 5
b1 9
1(
#200000
0(
0%
#210000
b10 "
b10 =
1(
#220000
0(
#230000
1(
#240000
0(
#250000
1(
#260000
0(
#270000
1(
#280000
0(
1%
0$
b10000001011 A
#290000
b11 5
b10 9
1(
#300000
0(
0%
#310000
1(
#320000
0(
#330000
1(
#340000
0(
#350000
1(
#360000
0(
#370000
1(
#380000
0(
1%
1$
b10000001010 A
#390000
b100 5
b101 9
1(
#400000
0(
0%
#410000
b1010 "
b1010 =
1(
#420000
0(
#430000
1(
#440000
0(
#450000
1(
#460000
0(
#470000
1(
#480000
0(
1%
0$
b10000001001 A
#490000
b101 5
b1010 9
1(
#500000
0(
0%
#510000
1(
#520000
0(
#530000
1(
#540000
0(
#550000
1(
#560000
0(
#570000
1(
#580000
0(
1%
b10000001000 A
#590000
b110 5
b100 9
1(
#600000
0(
0%
#610000
1(
#620000
0(
#630000
1(
#640000
0(
#650000
1(
#660000
0(
#670000
1(
#680000
0(
1%
1$
b10000000111 A
#690000
b111 5
b1001 9
1(
#700000
0(
0%
#710000
b1001010 "
b1001010 =
1(
#720000
0(
#730000
1(
#740000
0(
#750000
1(
#760000
0(
#770000
1(
#780000
0(
1%
0$
b10000000110 A
#790000
b1000 5
b10 9
1(
#800000
0(
0%
#810000
1(
#820000
0(
#830000
1(
#840000
0(
#850000
1(
#860000
0(
#870000
1(
#880000
0(
1%
b10000000101 A
#890000
b1001 5
b100 9
1(
#900000
0(
0%
#910000
1(
#920000
0(
#930000
1(
#940000
0(
#950000
1(
#960000
0(
#970000
1(
#980000
0(
1%
b10000000100 A
#990000
b1010 5
b1000 9
1(
#1000000
0(
0%
#1010000
1(
#1020000
0(
#1030000
1(
#1040000
0(
#1050000
1(
#1060000
0(
#1070000
1(
#1080000
0(
1%
b10000000011 A
#1090000
b1011 5
b0 9
1(
#1100000
0(
0%
#1110000
1(
#1120000
0(
#1130000
1(
#1140000
0(
#1150000
1(
#1160000
0(
#1170000
1(
#1180000
0(
1%
b10000000010 A
#1190000
b1100 5
1(
#1200000
0(
0%
#1210000
1(
#1220000
0(
#1230000
1(
#1240000
0(
#1250000
1(
#1260000
0(
#1270000
1(
#1280000
0(
1%
b10000000001 A
#1290000
b1101 5
1(
#1300000
0(
0%
#1310000
1(
#1320000
0(
#1330000
1(
#1340000
0(
#1350000
1(
#1360000
0(
#1370000
1(
#1380000
0(
1%
b10000000000 A
#1390000
b1110 5
1(
#1400000
0(
0%
#1410000
1(
#1420000
0(
#1430000
1(
#1440000
0(
#1450000
1(
#1460000
0(
#1470000
1(
#1480000
0(
1%
b1111111111 A
#1490000
b1111 5
1(
#1500000
0(
0%
#1510000
1(
#1520000
0(
#1530000
1(
#1540000
0(
#1550000
1(
#1560000
0(
#1570000
1(
#1580000
0(
1%
b1111111110 A
#1590000
b10000 5
1(
#1600000
0(
0%
#1610000
1(
#1620000
0(
#1630000
1(
#1640000
0(
#1650000
1(
#1660000
0(
#1670000
1(
#1680000
0(
1%
b1111111101 A
#1690000
b10001 5
1(
#1700000
0(
0%
#1710000
1(
#1720000
0(
#1730000
1(
#1740000
0(
#1750000
1(
#1760000
0(
#1770000
1(
#1780000
0(
1%
b1111111100 A
#1790000
b10010 5
1(
#1800000
0(
0%
#1810000
1(
#1820000
0(
#1830000
1(
#1840000
0(
#1850000
1(
#1860000
0(
#1870000
1(
#1880000
0(
1%
b1111111011 A
#1890000
b10011 5
1(
#1900000
0(
0%
#1910000
1(
#1920000
0(
#1930000
1(
#1940000
0(
#1950000
1(
#1960000
0(
#1970000
1(
#1980000
0(
1%
b1111111010 A
#1990000
b10100 5
1(
#2000000
0(
0%
#2010000
1(
#2020000
0(
#2030000
1(
#2040000
0(
#2050000
1(
#2060000
0(
#2070000
1(
#2080000
0(
1%
1$
b1111111001 A
#2090000
b10101 5
b1 9
1(
#2100000
0(
0%
#2110000
1#
b100000000000001001010 "
b100000000000001001010 =
1(
#2120000
0(
#2130000
b0 "
b0 =
b0 9
b0 5
0#
1(
#2140000
0(
#2150000
1(
#2160000
0(
#2170000
1(
#2180000
0(
1%
0$
b1111111000 A
#2190000
b1 5
1(
#2200000
0(
0%
#2210000
1(
#2220000
0(
#2230000
1(
#2240000
0(
#2250000
1(
#2260000
0(
#2270000
1(
#2280000
0(
1%
b1111110111 A
#2290000
b10 5
1(
#2300000
0(
0%
#2310000
1(
#2320000
0(
#2330000
1(
#2340000
0(
#2350000
1(
#2360000
0(
#2370000
1(
#2380000
0(
1%
1$
b1111110110 A
#2390000
b11 5
b1 9
1(
#2400000
0(
0%
#2410000
b100 "
b100 =
1(
#2420000
0(
#2430000
1(
#2440000
0(
#2450000
1(
#2460000
0(
#2470000
1(
#2480000
0(
1%
b1111110101 A
#2490000
b100 5
b11 9
1(
#2500000
0(
0%
#2510000
b1100 "
b1100 =
1(
#2520000
0(
#2530000
1(
#2540000
0(
#2550000
1(
#2560000
0(
#2570000
1(
#2580000
0(
1%
0$
b1111110100 A
#2590000
b101 5
b110 9
1(
#2600000
0(
0%
#2610000
1(
#2620000
0(
#2630000
1(
#2640000
0(
#2650000
1(
#2660000
0(
#2670000
1(
#2680000
0(
1%
b1111110011 A
#2690000
b110 5
b1100 9
1(
#2700000
0(
0%
#2710000
1(
#2720000
0(
#2730000
1(
#2740000
0(
#2750000
1(
#2760000
0(
#2770000
1(
#2780000
0(
1%
b1111110010 A
#2790000
b111 5
b1000 9
1(
#2800000
0(
0%
#2810000
1(
#2820000
0(
#2830000
1(
#2840000
0(
#2850000
1(
#2860000
0(
#2870000
1(
#2880000
0(
1%
1$
b1111110001 A
#2890000
b1000 5
b1 9
1(
#2900000
0(
0%
#2910000
b10001100 "
b10001100 =
1(
#2920000
0(
#2930000
1(
#2940000
0(
#2950000
1(
#2960000
0(
#2970000
1(
#2980000
0(
1%
b1111110000 A
#2990000
b1001 5
b11 9
1(
#3000000
0(
0%
#3010000
b110001100 "
b110001100 =
1(
#3020000
0(
#3030000
1(
#3040000
0(
#3050000
1(
#3060000
0(
#3070000
1(
#3080000
0(
1%
b1111101111 A
#3090000
b1010 5
b111 9
1(
#3100000
0(
0%
#3110000
b1110001100 "
b1110001100 =
1(
#3120000
0(
#3130000
1(
#3140000
0(
#3150000
1(
#3160000
0(
#3170000
1(
#3180000
0(
1%
0$
b1111101110 A
#3190000
b1011 5
b1110 9
1(
#3200000
0(
0%
#3210000
1(
#3220000
0(
#3230000
1(
#3240000
0(
#3250000
1(
#3260000
0(
#3270000
1(
#3280000
0(
1%
b1111101101 A
#3290000
b1100 5
b1100 9
1(
#3300000
0(
0%
#3310000
1(
#3320000
0(
#3330000
1(
#3340000
0(
#3350000
1(
#3360000
0(
#3370000
1(
#3380000
0(
1%
1$
b1111101100 A
#3390000
b1101 5
b1001 9
1(
#3400000
0(
0%
#3410000
b1001110001100 "
b1001110001100 =
1(
#3420000
0(
#3430000
1(
#3440000
0(
#3450000
1(
#3460000
0(
#3470000
1(
#3480000
0(
1%
b1111101011 A
#3490000
b1110 5
b11 9
1(
#3500000
0(
0%
#3510000
b11001110001100 "
b11001110001100 =
1(
#3520000
0(
#3530000
1(
#3540000
0(
#3550000
1(
#3560000
0(
#3570000
1(
#3580000
0(
1%
0$
b1111101010 A
#3590000
b1111 5
b110 9
1(
#3600000
0(
0%
#3610000
1(
#3620000
0(
#3630000
1(
#3640000
0(
#3650000
1(
#3660000
0(
#3670000
1(
#3680000
0(
1%
b1111101001 A
#3690000
b10000 5
b1100 9
1(
#3700000
0(
0%
#3710000
1(
#3720000
0(
#3730000
1(
#3740000
0(
#3750000
1(
#3760000
0(
#3770000
1(
#3780000
0(
1%
1$
b1111101000 A
#3790000
b10001 5
b1001 9
1(
#3800000
0(
0%
#3810000
b10011001110001100 "
b10011001110001100 =
1(
#3820000
0(
#3830000
1(
#3840000
0(
#3850000
1(
#3860000
0(
#3870000
1(
#3880000
0(
1%
b1111100111 A
#3890000
b10010 5
b11 9
1(
#3900000
0(
0%
#3910000
b110011001110001100 "
b110011001110001100 =
1(
#3920000
0(
#3930000
1(
#3940000
0(
#3950000
1(
#3960000
0(
#3970000
1(
#3980000
0(
1%
0$
b1111100110 A
#3990000
b10011 5
b110 9
1(
#4000000
0(
0%
#4010000
1(
#4020000
0(
#4030000
1(
#4040000
0(
#4050000
1(
#4060000
0(
#4070000
1(
#4080000
0(
1%
b1111100101 A
#4090000
b10100 5
b1100 9
1(
#4100000
0(
0%
#4110000
1(
#4120000
0(
#4130000
1(
#4140000
0(
#4150000
1(
#4160000
0(
#4170000
1(
#4180000
0(
1%
b1111100100 A
#4190000
b10101 5
b1000 9
1(
#4200000
0(
0%
#4210000
1#
1(
#4220000
0(
#4230000
b0 "
b0 =
b0 9
b0 5
0#
1(
#4240000
0(
#4250000
1(
#4260000
0(
#4270000
1(
#4280000
0(
1%
1$
b1111100011 A
#4290000
b1 5
b1 9
1(
#4300000
0(
0%
#4310000
b1 "
b1 =
1(
#4320000
0(
#4330000
1(
#4340000
0(
#4350000
1(
#4360000
0(
#4370000
1(
#4380000
0(
1%
0$
b1111100010 A
#4390000
b10 5
b10 9
1(
#4400000
0(
0%
#4410000
1(
#4420000
0(
#4430000
1(
#4440000
0(
#4450000
1(
#4460000
0(
#4470000
1(
#4480000
0(
1%
b1111100001 A
#4490000
b11 5
b100 9
1(
#4500000
0(
0%
#4510000
1(
#4520000
0(
#4530000
1(
#4540000
0(
#4550000
1(
#4560000
0(
#4570000
1(
#4580000
0(
1%
1$
b1111100000 A
#4590000
b100 5
b1001 9
1(
#4600000
0(
0%
#4610000
b1001 "
b1001 =
1(
#4620000
0(
#4630000
1(
#4640000
0(
#4650000
1(
#4660000
0(
#4670000
1(
#4680000
0(
1%
b1111011111 A
#4690000
b101 5
b11 9
1(
#4700000
0(
0%
#4710000
b11001 "
b11001 =
1(
#4720000
0(
#4730000
1(
#4740000
0(
#4750000
1(
#4760000
0(
#4770000
1(
#4780000
0(
1%
0$
b1111011110 A
#4790000
b110 5
b110 9
1(
#4800000
0(
0%
#4810000
1(
#4820000
0(
#4830000
1(
#4840000
0(
#4850000
1(
#4860000
0(
#4870000
1(
#4880000
0(
1%
b1111011101 A
#4890000
b111 5
b1100 9
1(
#4900000
0(
0%
#4910000
1(
#4920000
0(
#4930000
1(
#4940000
0(
#4950000
1(
#4960000
0(
#4970000
1(
#4980000
0(
1%
b1111011100 A
#4990000
b1000 5
b1000 9
1(
#5000000
0(
0%
#5010000
1(
#5020000
0(
#5030000
1(
#5040000
0(
#5050000
1(
#5060000
0(
#5070000
1(
#5080000
0(
1%
b1111011011 A
#5090000
b1001 5
b0 9
1(
#5100000
0(
0%
#5110000
1(
#5120000
0(
#5130000
1(
#5140000
0(
#5150000
1(
#5160000
0(
#5170000
1(
#5180000
0(
1%
1$
b1111011010 A
#5190000
b1010 5
b1 9
1(
#5200000
0(
0%
#5210000
b1000011001 "
b1000011001 =
1(
#5220000
0(
#5230000
1(
#5240000
0(
#5250000
1(
#5260000
0(
#5270000
1(
#5280000
0(
1%
b1111011001 A
#5290000
b1011 5
b11 9
1(
#5300000
0(
0%
#5310000
b11000011001 "
b11000011001 =
1(
#5320000
0(
#5330000
1(
#5340000
0(
#5350000
1(
#5360000
0(
#5370000
1(
#5380000
0(
1%
b1111011000 A
#5390000
b1100 5
b111 9
1(
#5400000
0(
0%
#5410000
b111000011001 "
b111000011001 =
1(
#5420000
0(
#5430000
1(
#5440000
0(
#5450000
1(
#5460000
0(
#5470000
1(
#5480000
0(
1%
0$
b1111010111 A
#5490000
b1101 5
b1110 9
1(
#5500000
0(
0%
#5510000
1(
#5520000
0(
#5530000
1(
#5540000
0(
#5550000
1(
#5560000
0(
#5570000
1(
#5580000
0(
1%
1$
b1111010110 A
#5590000
b1110 5
b1101 9
1(
#5600000
0(
0%
#5610000
b10111000011001 "
b10111000011001 =
1(
#5620000
0(
#5630000
1(
#5640000
0(
#5650000
1(
#5660000
0(
#5670000
1(
#5680000
0(
1%
b1111010101 A
#5690000
b1111 5
b1011 9
1(
#5700000
0(
0%
#5710000
b110111000011001 "
b110111000011001 =
1(
#5720000
0(
#5730000
1(
#5740000
0(
#5750000
1(
#5760000
0(
#5770000
1(
#5780000
0(
1%
b1111010100 A
#5790000
b10000 5
b111 9
1(
#5800000
0(
0%
#5810000
b1110111000011001 "
b1110111000011001 =
1(
#5820000
0(
#5830000
1(
#5840000
0(
#5850000
1(
#5860000
0(
#5870000
1(
