Alex/test_builds/parser/src/HT_5.sv
`default_nettype none
`timescale 1ns / 1ps


module HT_5(
		input wire clk,
		input wire rst,

		input wire axiiv,
		input wire axiid,
		output logic err,
		output logic axiov,
		output logic [3:0] x_val,
		output logic [3:0] y_val
	);

  parameter MAX_BITS = 8;

	logic [7:0] buffer;
	logic [3:0] bit_counter;    //i don't think any word lengths are greater than 12.

	logic [9:0] word;

	assign {axiov, err, x_val, y_val} = word;

	always_ff @(posedge clk) begin
		if (rst) begin
			bit_counter <= 0;
			buffer <= 0;
		end else begin
			if (axiov || err) begin
				bit_counter <= axiiv ? 1 : 0;
				buffer <= axiiv ? {axiid, 7'b00} : 8'b0;
			end else if (bit_counter > MAX_BITS) begin
				bit_counter <= 0;
				buffer <= 0;        //clear everything if no word can be found.
			end else if (axiiv) begin
				bit_counter <= bit_counter + 1;
				case (bit_counter)
						4'd0 : buffer[7] <= axiid;
						4'd1 : buffer[6] <= axiid;
						4'd2 : buffer[5] <= axiid;
						4'd3 : buffer[4] <= axiid;
						4'd4 : buffer[3] <= axiid;
						4'd5 : buffer[2] <= axiid;
						4'd6 : buffer[1] <= axiid;
						4'd7 : buffer[0] <= axiid;
        endcase
			end
		end
	end

	always_comb begin
		case (bit_counter)
			4'd0 : word = 10'b00_0000_0000;
			4'd1 : begin
					case (buffer[7])
						1'b1 : word = 10'b10_0000_0000;
						default : word = 10'b00_0000_0000;
					endcase
				end
			4'd2 : word = 10'b00_0000_0000;
			4'd3 : begin
					case (buffer[7:5])
						3'b010 : word = 10'b10_0000_0001;
						3'b011 : word = 10'b10_0001_0000;
						3'b001 : word = 10'b10_0001_0001;
						default : word = 10'b00_0000_0000;
					endcase
				end
			4'd4 : word = 10'b00_0000_0000;
			4'd5 : word = 10'b00_0000_0000;
			4'd6 : begin
					case (buffer[7:2])
						6'b000110 : word = 10'b10_0000_0010;
						6'b000100 : word = 10'b10_0001_0010;
						6'b000111 : word = 10'b10_0010_0000;
						6'b000101 : word = 10'b10_0010_0001;
						6'b000001 : word = 10'b10_0011_0001;
						default : word = 10'b00_0000_0000;
					endcase
				end
			4'd7 : begin
					case (buffer[7:1])
						7'b0000101 : word = 10'b10_0000_0011;
						7'b0000100 : word = 10'b10_0001_0011;
						7'b0000111 : word = 10'b10_0010_0010;
						7'b0000110 : word = 10'b10_0011_0000;
						7'b0000001 : word = 10'b10_0011_0010;
						default : word = 10'b00_0000_0000;
					endcase
				end
			4'd8 : begin
					case (buffer[7:0])
						8'b00000001 : word = 10'b10_0010_0011;
						8'b00000000 : word = 10'b10_0011_0011;
						default : word = 10'b00_0000_0000;
					endcase
				end
			default : word = 10'b01_0000_0000;
		endcase
	end
endmodule


`default_nettype wire

Alex/test_builds/parser/sim/HT_1_tb.sv
`default_nettype none
`timescale 1ns / 1ps

module HT_1_tb;

logic clk;
logic rst;
logic axiiv;
logic axiid;

logic err;
logic axiov;
logic [3:0] x_val;
logic [3:0] y_val;

HT_5 UUT (clk, rst, axiiv, axiid, err, axiov, x_val, y_val);

logic [18:0] code;

always begin
  #10;
  clk = !clk;     //clock cycles now happend every 20!
end

initial begin
  $dumpfile("sim/HT_1_sim.vcd");
  $dumpvars(0, HT_1_tb);
  $display("Starting Sim");

  code = 19'b001_000110_0000101_010;

  clk = 0;
  rst = 0;

  axiiv = 0;
  axiid = 0;    //make the inputs 0 too!
  #20;
  rst = 1;
  #20;
  rst = 0;

  //TRANSMIT DESTINATION

  for (int i = 0; i < 19; i += 1) begin
    axiiv = 1;
    axiid = code[18-i];
    #20;
    axiiv = 0;
  end
  #200;


  $display("Finishing Sim");
  $finish;

end
endmodule

`default_nettype wire

Alex/test_builds/parser/sim/HT_1_sim.vcd
$date
	Sat Dec 03 17:43:38 2022
$end
$version
	Icarus Verilog
$end
$timescale
	1ps
$end
$scope module HT_1_tb $end
$var wire 4 ! y_val [3:0] $end
$var wire 4 " x_val [3:0] $end
$var wire 1 # err $end
$var wire 1 $ axiov $end
$var reg 1 % axiid $end
$var reg 1 & axiiv $end
$var reg 1 ' clk $end
$var reg 19 ( code [18:0] $end
$var reg 1 ) rst $end
$scope module UUT $end
$var wire 1 % axiid $end
$var wire 1 & axiiv $end
$var wire 1 ' clk $end
$var wire 1 ) rst $end
$var wire 4 * y_val [3:0] $end
$var wire 4 + x_val [3:0] $end
$var wire 1 # err $end
$var wire 1 $ axiov $end
$var parameter 32 , MAX_BITS $end
$var reg 4 - bit_counter [3:0] $end
$var reg 8 . buffer [7:0] $end
$var reg 10 / word [9:0] $end
$upscope $end
$scope begin $ivl_for_loop0 $end
$var integer 32 0 i [31:0] $end
$upscope $end
$upscope $end
$enddefinitions $end
$comment Show the parameter values. $end
$dumpall
b1000 ,
$end
#0
$dumpvars
b0 0
b100000000 /
bx .
bx -
b0 +
b0 *
0)
b10001100000101010 (
0'
0&
0%
0$
1#
b0 "
b0 !
$end
#10000
0#
b0 /
b0 .
b0 -
1'
#20000
0'
1)
#30000
1'
#40000
0'
1&
0)
#50000
b1 -
1'
#60000
0'
b1 0
1&
#70000
b10 -
1'
#80000
0'
1%
b10 0
1&
#90000
1$
b1 "
b1 +
b1 !
b1 *
b1000010001 /
b100000 .
b11 -
1'
#100000
0'
0%
b11 0
1&
#110000
0$
b0 "
b0 +
b0 !
b0 *
b0 /
b0 .
b1 -
1'
#120000
0'
b100 0
1&
#130000
b10 -
1'
#140000
0'
b101 0
1&
#150000
b11 -
1'
#160000
0'
1%
b110 0
1&
#170000
b10000 .
b100 -
1'
#180000
0'
b111 0
1&
#190000
b11000 .
b101 -
1'
#200000
0'
0%
b1000 0
1&
#210000
1$
b10 !
b10 *
b1000000010 /
b110 -
1'
#220000
0'
b1001 0
1&
#230000
0$
b0 !
b0 *
b0 /
b0 .
b1 -
1'
#240000
0'
b1010 0
1&
#250000
b10 -
1'
#260000
0'
b1011 0
1&
#270000
b11 -
1'
#280000
0'
b1100 0
1&
#290000
b100 -
1'
#300000
0'
1%
b1101 0
1&
#310000
b1000 .
b101 -
1'
#320000
0'
0%
b1110 0
1&
#330000
b110 -
1'
#340000
0'
1%
b1111 0
1&
#350000
1$
b11 !
b11 *
b1000000011 /
b1010 .
b111 -
1'
#360000
0'
0%
b10000 0
1&
#370000
0$
b0 !
b0 *
b0 /
b0 .
b1 -
1'
#380000
0'
1%
b10001 0
1&
#390000
b1000000 .
b10 -
1'
#400000
0'
0%
b10010 0
1&
#410000
1$
b1 !
b1 *
b1000000001 /
b11 -
1'
#420000
0'
b10011 0
0&
#430000
0$
b0 !
b0 *
b0 /
b0 .
b0 -
1'
