Alex/test_builds/parser/src/header.sv
`timescale 1ns / 1ps
`default_nettype none


/*
STATUS: WORKING
  tested a few different ways given the 4 bytes are inputted consecutively. right now there is nothing to reset
  the internal header_byte_counter, so if it stops getting the bytes in halfway, but no rst signal is sent in,
  this shit will output data at the wrong time.
  dont know how to fix this realistically, unless we take the byte_counter as an input.
  but that method is not really sustainable for downstream stuff (cus of the CRC16 check throwing the byte count off)
  so i don't want to make that counter into some kind of global system.
  I would rather just ensure that the entire frame is loaded (ti doesn't quite reading in the frame halfway).
  If that system breaks, we have the reset button to save the system.
*/

module header(
    input wire clk,
    input wire rst,
    input wire [7:0] axiid,
    input wire axiiv,

    output logic axiov,
    output logic prot,
    output logic [8:0] bitrate,
    output logic [15:0] samp_rate,
    output logic padding,
    output logic private,
    output logic [1:0] mode,
    output logic [1:0] mode_ext,
    output logic [1:0] emphasis,
    output logic [8:0] frame_sample,
    output logic [2:0] slot_size,
    output logic [10:0] frame_size
);
    logic [31:0] header;
    logic [1:0] header_byte_counter;    //counts to 3 and then recycles...

    always_ff @(posedge clk) begin
        if (rst) begin
          header <= 0;
          header_byte_counter <= 0;
          axiov <= 0;
        end else begin
            if (axiiv) begin
              header <= {header[23:0], axiid};

                if (header_byte_counter == 2'b11) begin
                  axiov <= 1;   //this means the 4 bytes for the header have been read in now!
                  header_byte_counter <= 0;     //reset the byte counter to 0 again...
                end else begin
                  header_byte_counter <= header_byte_counter + 1;   //increment the header byte counter
                  axiov <= 0;
                end

            end else begin
              axiov <= 0;
            end
        end
    end

    always_comb begin
        case(header[15:12])
            4'b0001 : bitrate = 9'd32;
            4'b0010 : bitrate = 9'd40;
            4'b0011 : bitrate = 9'd48;
            4'b0100 : bitrate = 9'd56;
            4'b0101 : bitrate = 9'd64;
            4'b0110 : bitrate = 9'd80;
            4'b0111 : bitrate = 9'd96;
            4'b1000 : bitrate = 9'd112;
            4'b1001 : bitrate = 9'd128;
            4'b1010 : bitrate = 9'd160;
            4'b1011 : bitrate = 9'd192;
            4'b1100 : bitrate = 9'd224;
            4'b1101 : bitrate = 9'd256;
            4'b1110 : bitrate = 9'd320;
            default : bitrate = 9'd0;
        endcase
        case(header[11:10])
            2'b00 : samp_rate = 16'd44100;
            2'b01 : samp_rate = 16'd48000;
            2'b10 : samp_rate = 16'd32000;
        default samp_rate = 16'd0;
    endcase
    end

    assign prot = header[16];

    assign padding = header[9];

    assign private = header[8];

    assign mode = header[7:6];

    assign mode_ext = header[5:4];

    assign emphasis = header[1:0];

    assign frame_sample = 9'd384;

    assign slot_size = 3'd4;

    //compute the frame size according to a look up table (so we dont have to divide by 44100):
    //note that this HAS to be done within a clock cycle because the frame parsing takes this information into account
    always_comb begin
      case(bitrate)
          9'd32   :   frame_size = padding ? (11'd104  + 1) : (11'd104) ;
          9'd40   :   frame_size = padding ? (11'd130  + 1) : (11'd130) ;
          9'd48   :   frame_size = padding ? (11'd156  + 1) : (11'd156) ;
          9'd56   :   frame_size = padding ? (11'd182  + 1) : (11'd182) ;
          9'd64   :   frame_size = padding ? (11'd208  + 1) : (11'd208) ;
          9'd80   :   frame_size = padding ? (11'd261  + 1) : (11'd261) ;
          9'd96   :   frame_size = padding ? (11'd313  + 1) : (11'd313) ;
          9'd112  :   frame_size = padding ? (11'd365  + 1) : (11'd365) ;
          9'd128  :   frame_size = padding ? (11'd417  + 1) : (11'd417) ;
          9'd160  :   frame_size = padding ? (11'd522  + 1) : (11'd522) ;
          9'd192  :   frame_size = padding ? (11'd626  + 1) : (11'd626) ;
          9'd224  :   frame_size = padding ? (11'd731  + 1) : (11'd731) ;
          9'd256  :   frame_size = padding ? (11'd835  + 1) : (11'd835) ;
          9'd320  :   frame_size = padding ? (11'd1044 + 1) : (11'd1044);
          default :   frame_size = 9'd0;
      endcase

    end

    //frame size cases compared to bitrate cases:
    /*
    bitrates    -> [0,  32,  40,  48,  56,  64,  80,  96, 112, 128, 160, 192, 224, 256,  320, 0]
    frame sizes -> [0, 104, 130, 156, 182, 208, 261, 313, 365, 417, 522, 626, 731, 835, 1044, 0]
    */
    //note that this LUT is only possible by assuming the MPEG-1 Layer III 44.1kHz stuff too.
endmodule

`default_nettype wire

Alex/test_builds/parser/src/sd_plexer.sv
`timescale 1ns / 1ps
`default_nettype none

/*
this module directs the output of the SD card reader to other modules
it takes in a byte (from the sd card reader, sd_out)
and based on the byte counter (some value from 0-511)
it directs the info to:
  header
  side_info_1 (1 channel side information parser)
  side_info_2 (2 channel side information parser)
  fifo_buffer (main data...)
*/

module sd_plexer(
    input wire clk,
    input wire rst,

    input wire sd_iv,
    input wire [7:0] sd_din,

    input wire header_iv,     //pulses for one clock cycle, tells us whether the header input data is valid or not
    input wire [1:0] mode,    //this is from the header module (circular logic lmao)
    input wire prot,    //this is whether or not the header has a CRC16 protection (takes 2 more bytes after header), 1 == no protection
    input wire [10:0] frame_size,    //computed number of bytes in the frame...

    output logic header_ov,
    output logic crc_16_ov,
    output logic side_info_1_ov,
    output logic side_info_2_ov,
    output logic fifo_buffer_ov,      //output valids for all the downstream modules

    output logic [7:0] d_out
  );

  logic [8:0] byte_counter;      //this counts from 0 to 511 (512 bytes), so it only needs 9 bits...
  logic [4:0] output_codeword;

  assign {header_ov, crc_16_ov, side_info_1_ov, side_info_2_ov, fifo_buffer_ov} = output_codeword;
  assign main_data_length = frame_size - (header_length + crc_length + side_info_length);
  assign d_out = sd_din;

  logic [3:0] header_length;
  logic [1:0] crc_length;
  logic [5:0] side_info_length;
  logic [10:0] main_data_length;

  always_ff @(posedge clk) begin
    if (rst) begin
      byte_counter    <= 0;
      output_codeword <= 0;
      header_length   <= 4'd4;
    end else begin

            if (sd_iv) begin
              byte_counter <= byte_counter + 1;

              if (byte_counter < header_length) begin
                output_codeword                 <= 5'b10000;
              end else if (byte_counter < (header_length + crc_length)) begin
                output_codeword                 <= 5'b01000;
              end else if (byte_counter < (header_length + crc_length + side_info_length)) begin
                if (mode == 3) output_codeword  <= 5'b00100;
                else output_codeword            <= 5'b00010;
              end else if (byte_counter < (header_length + crc_length + side_info_length + main_data_length)) begin
                output_codeword                 <= 5'b00001;
              end else begin
                output_codeword                 <= 5'b00000;
              end
            end else begin
              output_codeword                   <= 5'b00000;
            end


            //adjust frame delination parameters if the header has been fully processed.
            if (header_iv) begin
                header_length                   <= 4'd4;

                if (prot) crc_length            <= 2'd0;
                else crc_length                 <= 2'd2;

                if (mode == 3) side_info_length <= 6'd17;
                else side_info_length           <= 6'd32;
            end

      end

    end

endmodule


`default_nettype wire

Sam/test_builds/parser/sim/sd_plexer_tb.sv
`default_nettype none
`timescale 1ns / 1ps

module plexer_tb;

  logic clk;
  logic rst;

  logic sd_iv;
  logic [7:0] sd_din;

  logic header_iv;     //pulses for one clock cycle, tells us whether the header input data is valid or not
  logic [1:0] mode;    //this is from the header module (circular logic lmao)
  logic prot;    //this is whether or not the header has a CRC16 protection (takes 2 more bytes after header), 1 == no protection
  logic [10:0] frame_size;    //computed number of bytes in the frame...
  logic [8:0] bitrate;
  logic [15:0] samp_rate;
  logic padding;
  logic private;
  logic [1:0] mode_ext;
  logic [1:0] emphasis;
  logic [8:0] frame_sample;
  logic [2:0] slot_size;
  logic header_ov;
  logic crc_16_ov;
  logic side_info_1_ov;
  logic side_info_2_ov;
  logic fifo_buffer_ov;      //output valids for all the downstream modules

  logic [7:0] d_out;
  logic [8:0] byte_counter;


  logic [3343:0] frame_code;


  sd_plexer p (
      clk,
      rst,

      sd_iv,
      sd_din,

      header_iv,     //pulses for one clock cycle, tells us whether the header input data is valid or not
      mode,    //this is from the header module (circular logic lmao)
      prot,    //this is whether or not the header has a CRC16 protection (takes 2 more bytes after header), 1 == no protection
      frame_size,    //computed number of bytes in the frame...

      header_ov,
      crc_16_ov,
      side_info_1_ov,
      side_info_2_ov,
      fifo_buffer_ov,      //output valids for all the downstream modules

      d_out
    );

  header h (
      clk,
      rst,
      d_out,
      header_ov,

      header_iv,
      prot,
      bitrate,
      samp_rate,
      padding,
      private,
      mode,
      mode_ext,
      emphasis,
      frame_sample,
      slot_size,
      frame_size
    );


  always begin
    #10;
    clk = !clk;     //clock cycles now happend every 20!
  end

  initial begin
    $dumpfile("sim/plexer_sim.vcd");
    $dumpvars(0, plexer_tb);
    $display("Starting Sim");

    frame_code = 3344'hfffb92642082f40e6056af69000000000d20e000010ec95f58cd18554800003480000004e6236c9abab64a1ac24681c3c94162c58a85f6b9b7ef89aaa18aae4d53777f4b536ad8e1f0f57c5c4691349ed3d713d71777fd13abfdcd7cf095e4e452c263772c2000462b01b908a4da32745b6b301352861e7acef35ca684bd116bd59e7fa6ad4b52db1fa7b517c2b543b019148fadd2b081341fbfa8b9151af93746a325fcafeb1db19eb775f62bb31285a560a77692ce942e92114862ee0d8e3b1667217b6a975b77bf76dbdadcce24227829da2dbc5a7fba45effb02051001047e06ec78c45e4ff6f9385c85b1464c54050529543962187cc4a54701d101f6899000010ea13ec00cf65b2168de5216ad32aa9f940d554a6f393d51ad38d7918a65a71597352dca19881c1576421086e2d39fc3eeb4aa68e70d9213667015044390a0b810624382c6e6de752630abae6a664a1575741f3b514a6c128200752c60644050640ac4d45dc952c8eadb45fa030a0445e3027e9017c32bc292eb8b15c38374a980b51451a7975812659a7398cdb41e7e184044ef08eecd375172e6fecdddec;

    clk = 0;
    rst = 0;

    sd_iv = 0;
    sd_din = 0;    //make the inputs 0 too!
    #20;
    rst = 1;
    #20;
    rst = 0;

    //TRANSMIT DESTINATION

    for (int i = 0; i < 418; i += 1) begin
      sd_iv = 1;
      sd_din = frame_code[(3343 - (8*i)) -: 8];
      #20;

      sd_iv = 0;
      #100;
    end


    $display("Finishing Sim");
    $finish;

  end

endmodule


`default_nettype wire

Alex/test_builds/parser/sim/plexer_sim.vcd
$date
	Fri Dec 02 19:58:37 2022
$end
$version
	Icarus Verilog
$end
$timescale
	1ps
$end
$scope module plexer_tb $end
$var wire 9 ! frame_sample [8:0] $end
$var wire 3 " slot_size [2:0] $end
$var wire 1 # side_info_2_ov $end
$var wire 1 $ side_info_1_ov $end
$var wire 16 % samp_rate [15:0] $end
$var wire 1 & prot $end
$var wire 1 ' private $end
$var wire 1 ( padding $end
$var wire 2 ) mode_ext [1:0] $end
$var wire 2 * mode [1:0] $end
$var wire 1 + header_ov $end
$var wire 1 , header_iv $end
$var wire 11 - frame_size [10:0] $end
$var wire 1 . fifo_buffer_ov $end
$var wire 2 / emphasis [1:0] $end
$var wire 8 0 d_out [7:0] $end
$var wire 1 1 crc_16_ov $end
$var wire 9 2 bitrate [8:0] $end
$var reg 1 3 clk $end
$var reg 3344 4 frame_code [3343:0] $end
$var reg 1 5 rst $end
$var reg 8 6 sd_din [7:0] $end
$var reg 1 7 sd_iv $end
$scope module h $end
$var wire 1 3 clk $end
$var wire 9 8 frame_sample [8:0] $end
$var wire 1 5 rst $end
$var wire 3 9 slot_size [2:0] $end
$var wire 1 & prot $end
$var wire 1 ' private $end
$var wire 1 ( padding $end
$var wire 2 : mode_ext [1:0] $end
$var wire 2 ; mode [1:0] $end
$var wire 2 < emphasis [1:0] $end
$var wire 1 + axiiv $end
$var wire 8 = axiid [7:0] $end
$var reg 1 , axiov $end
$var reg 9 > bitrate [8:0] $end
$var reg 11 ? frame_size [10:0] $end
$var reg 32 @ header [31:0] $end
$var reg 2 A header_byte_counter [1:0] $end
$var reg 16 B samp_rate [15:0] $end
$upscope $end
$scope module p $end
$var wire 1 3 clk $end
$var wire 8 C d_out [7:0] $end
$var wire 11 D frame_size [10:0] $end
$var wire 1 , header_iv $end
$var wire 2 E mode [1:0] $end
$var wire 1 & prot $end
$var wire 1 5 rst $end
$var wire 8 F sd_din [7:0] $end
$var wire 1 7 sd_iv $end
$var wire 1 # side_info_2_ov $end
$var wire 1 $ side_info_1_ov $end
$var wire 11 G main_data_length [10:0] $end
$var wire 1 + header_ov $end
$var wire 1 . fifo_buffer_ov $end
$var wire 1 1 crc_16_ov $end
$var reg 9 H byte_counter [8:0] $end
$var reg 2 I crc_length [1:0] $end
$var reg 4 J header_length [3:0] $end
$var reg 5 K output_codeword [4:0] $end
$var reg 6 L side_info_length [5:0] $end
$upscope $end
$scope begin $ivl_for_loop0 $end
$var integer 32 M i [31:0] $end
$upscope $end
$upscope $end
$enddefinitions $end
$comment Show the parameter values. $end
$dumpall
$end
#0
$dumpvars
b0 M
bx L
bx K
bx J
bx I
bx H
bx G
b0 F
bx E
b0 D
b0 C
b0 B
bx A
bx @
b0 ?
b0 >
b0 =
bx <
bx ;
bx :
b100 9
b110000000 8
07
b0 6
05
b11111111111110111001001001100100001000001000001011110100000011100110000001010110101011110110100100000000000000000000000000000000000011010010000011100000000000000000000100001110110010010101111101011000110011010001100001010101010010000000000000000000001101001000000000000000000000000000010011100110001000110110110010011010101110101011011001001010000110101100001001000110100000011100001111001001010000010110001011000101100010101000010111110110101110011011011111101111100010011010101010100001100010101010111001001101010100110111011101111111010010110101001101101010110110001110000111110000111101010111110001011100010001101001000100110100100111101101001111010111000100111101011100010111011101111111110100010011101010111111110111001101011111001111000010010101111001001110010001010010110000100110001101110111001011000010000000000000010001100010101100000001101110010000100010100100110110100011001001110100010110110110101100110000000100110101001010000110000111100111101011001110111100110101110010100110100001001011110100010001011010111101010110011110011111111010011010101101010010110101001011011011000111111010011110110101000101111100001010110101010000111011000000011001000101001000111110101101110100101011000010000001001101000001111110111111101010001011100100010101000110101111100100110111010001101010001100100101111111001010111111101011000111011011000110011110101101110111010111110110001010111011001100010010100001011010010101100000101001110111011010010010110011101001010000101110100100100001000101001000011000101110111000001101100011100011101100010110011001110010000101111011011010101001011101011011011101111011111101110110110110111101101011011100110011100010010000100010011110000010100111011010001011011011110001011010011111111011101001000101111011111111101100000010000001010001000000000001000001000111111000000110111011000111100011000100010111100100111111110110111110010011100001011100100001011011000101000110010011000101010000000101000001010010100101010100001110010110001000011000011111001100010010100101010001110000000111010001000000011111011010001001100100000000000000000001000011101010000100111110110000000000110011110110010110110010000101101000110111100101001000010110101011010011001010101010100111111001010000001101010101010100101001101111001110010011110101010001101011010011100011010111100100011000101001100101101001110001010110010111001101010010110111001010000110011000100000011100000101010111011001000010000100001000011011100010110100111001111111000011111011101011010010101010011010001110011100001101100100100001001101100110011100000001010100000100010000111001000010100000101110000001000001100010010000111000001011000110111001101101111001110101001001100011000010101011101011100110101001100110010010100001010101110101011101000001111100111011010100010100101001101100000100101000001000000000011101010010110001100000011001000100000001010000011001000000101011000100110101000101110111001001010100101100100011101010110110110100010111111010000000110000101000000100010001011110001100000010011111101001000000010111110000110010101111000010100100101110101110001011000101011100001110000011011101001010100110000000101101010001010001010001101001111001011101011000000100100110010110011010011100111001100011001101101101000001111001111110000110000100000001000100111011110000100011101110110011010011011101010001011100101110011011111110110011011101110111101100 4
03
b0 2
x1
b0 0
bx /
x.
b0 -
x,
x+
bx *
bx )
x(
x'
x&
b0 %
x$
x#
b100 "
b110000000 !
$end
#10000
0+
01
0$
0#
0.
b0 K
0,
13
#20000
03
15
#30000
b1010110001000100 %
b1010110001000100 B
0&
0(
0'
b0 *
b0 ;
b0 E
b0 )
b0 :
b0 /
b0 <
b0 A
b0 @
b100 J
b0 H
13
#40000
03
b11111111 0
b11111111 =
b11111111 C
b11111111 6
b11111111 F
17
05
#50000
1+
b10000 K
b1 H
13
#60000
03
07
#70000
b11 *
b11 ;
b11 E
b11 )
b11 :
b11 /
b11 <
0+
b1 A
b11111111 @
b0 K
13
#80000
03
#90000
13
#100000
03
#110000
13
#120000
03
#130000
13
#140000
03
#150000
13
#160000
03
b11111011 0
b11111011 =
b11111011 C
b11111011 6
b11111011 F
17
b1 M
#170000
1+
b10000 K
b10 H
13
#180000
03
07
#190000
b0 %
b0 B
1(
1'
0+
b10 A
b1111111111111011 @
b0 K
13
#200000
03
#210000
13
#220000
03
#230000
13
#240000
03
#250000
13
#260000
03
#270000
13
#280000
03
b10010010 0
b10010010 =
b10010010 C
b10010010 6
b10010010 F
17
b10 M
#290000
1+
b10000 K
b11 H
13
#300000
03
07
#310000
b111110100000000 %
b111110100000000 B
1&
b10 *
b10 ;
b10 E
b1 )
b1 :
b10 /
b10 <
0+
b11 A
b111111111111101110010010 @
b0 K
13
#320000
03
#330000
13
#340000
03
#350000
13
#360000
03
#370000
13
#380000
03
#390000
13
#400000
03
b1100100 0
b1100100 =
b1100100 C
b1100100 6
b1100100 F
17
b11 M
#410000
1+
b10000 K
b100 H
13
#420000
03
07
#430000
b110100010 -
b110100010 ?
b110100010 D
b1010110001000100 %
b1010110001000100 B
b10000000 2
b10000000 >
0'
b1 *
b1 ;
b1 E
b10 )
b10 :
b0 /
b0 <
0+
b0 A
1,
b11111111111110111001001001100100 @
b0 K
13
#440000
03
#450000
b101111110 G
b100000 L
b0 I
0,
13
#460000
03
#470000
13
#480000
03
#490000
13
#500000
03
#510000
13
#520000
03
b100000 0
b100000 =
b100000 C
b100000 6
b100000 F
17
b100 M
#530000
1#
b10 K
b101 H
13
#540000
03
07
#550000
0#
b0 K
13
#560000
03
#570000
13
#580000
03
#590000
13
#600000
03
#610000
13
#620000
03
#630000
13
#640000
03
b10000010 0
b10000010 =
b10000010 C
b10000010 6
b10000010 F
17
b101 M
#650000
1#
b10 K
b110 H
13
#660000
03
07
#670000
0#
b0 K
13
#680000
03
#690000
13
#700000
03
#710000
13
#720000
03
#730000
13
#740000
03
#750000
13
#760000
03
b11110100 0
b11110100 =
b11110100 C
b11110100 6
b11110100 F
17
b110 M
#770000
1#
b10 K
b111 H
13
#780000
03
07
#790000
0#
b0 K
13
#800000
03
#810000
13
#820000
03
#830000
13
#840000
03
#850000
13
#860000
03
#870000
13
#880000
03
b1110 0
b1110 =
b1110 C
b1110 6
b1110 F
17
b111 M
#890000
1#
b10 K
b1000 H
13
#900000
03
07
#910000
0#
b0 K
13
#920000
03
#930000
13
#940000
03
#950000
13
#960000
03
#970000
13
#980000
03
#990000
13
#1000000
03
b1100000 0
b1100000 =
b1100000 C
b1100000 6
b1100000 F
17
b1000 M
#1010000
1#
b10 K
b1001 H
13
#1020000
03
07
#1030000
0#
b0 K
13
#1040000
03
#1050000
13
#1060000
03
#1070000
13
#1080000
03
#1090000
13
#1100000
03
#1110000
13
#1120000
03
b1010110 0
b1010110 =
b1010110 C
b1010110 6
b1010110 F
17
b1001 M
#1130000
1#
b10 K
b1010 H
13
#1140000
03
07
#1150000
0#
b0 K
13
#1160000
03
#1170000
13
#1180000
03
#1190000
13
#1200000
03
#1210000
13
#1220000
03
#1230000
13
#1240000
03
b10101111 0
b10101111 =
b10101111 C
b10101111 6
b10101111 F
17
b1010 M
#1250000
1#
b10 K
b1011 H
13
#1260000
03
07
#1270000
0#
b0 K
13
#1280000
03
#1290000
13
#1300000
03
#1310000
13
#1320000
03
#1330000
13
#1340000
03
#1350000
13
#1360000
03
b1101001 0
b1101001 =
b1101001 C
b1101001 6
b1101001 F
17
b1011 M
#1370000
1#
b10 K
b1100 H
13
#1380000
03
07
#1390000
0#
b0 K
13
#1400000
03
#1410000
13
#1420000
03
#1430000
13
#1440000
03
#1450000
13
#1460000
03
#1470000
13
#1480000
03
b0 0
b0 =
b0 C
b0 6
b0 F
17
b1100 M
#1490000
1#
b10 K
b1101 H
13
#1500000
03
07
#1510000
0#
b0 K
13
#1520000
03
#1530000
13
#1540000
03
#1550000
13
#1560000
03
#1570000
13
#1580000
03
#1590000
13
#1600000
03
17
b1101 M
#1610000
1#
b10 K
b1110 H
13
#1620000
03
07
#1630000
0#
b0 K
13
#1640000
03
#1650000
13
#1660000
03
#1670000
13
#1680000
03
#1690000
13
#1700000
03
#1710000
13
#1720000
03
17
b1110 M
#1730000
1#
b10 K
b1111 H
13
#1740000
03
07
#1750000
0#
b0 K
13
#1760000
03
#1770000
13
#1780000
03
#1790000
13
#1800000
03
#1810000
13
#1820000
03
#1830000
13
#1840000
03
17
b1111 M
#1850000
1#
b10 K
b10000 H
13
#1860000
03
07
#1870000
0#
b0 K
13
#1880000
03
#1890000
13
#1900000
03
#1910000
13
#1920000
03
#1930000
13
#1940000
03
#1950000
13
#1960000
03
b1101 0
b1101 =
b1101 C
b1101 6
b1101 F
17
b10000 M
#1970000
1#
b10 K
b10001 H
13
#1980000
03
07
#1990000
0#
b0 K
13
#2000000
03
#2010000
13
#2020000
03
#2030000
13
#2040000
03
#2050000
13
#2060000
03
#2070000
13
#2080000
03
b100000 0
b100000 =
b100000 C
b100000 6
b100000 F
17
b10001 M
#2090000
1#
b10 K
b10010 H
13
#2100000
03
07
#2110000
0#
b0 K
13
#2120000
03
#2130000
13
#2140000
03
#2150000
13
#2160000
03
#2170000
13
#2180000
03
#2190000
13
#2200000
03
b11100000 0
b11100000 =
b11100000 C
b11100000 6
b11100000 F
17
b10010 M
#2210000
1#
b10 K
b10011 H
13
#2220000
03
07
#2230000
0#
b0 K
13
#2240000
03
#2250000
13
#2260000
03
#2270000
13
#2280000
03
#2290000
13
#2300000
03
#2310000
13
#2320000
03
b0 0
b0 =
b0 C
b0 6
b0 F
17
b10011 M
#2330000
1#
b10 K
b10100 H
13
#2340000
03
07
#2350000
0#
b0 K
13
#2360000
03
#2370000
13
#2380000
03
#2390000
13
#2400000
03
#2410000
13
#2420000
03
#2430000
13
#2440000
03
b1 0
b1 =
b1 C
b1 6
b1 F
17
b10100 M
#2450000
1#
b10 K
b10101 H
13
#2460000
03
07
#2470000
0#
b0 K
13
#2480000
03
#2490000
13
#2500000
03
#2510000
13
#2520000
03
#2530000
13
#2540000
03
#2550000
13
#2560000
03
b1110 0
b1110 =
b1110 C
b1110 6
b1110 F
17
b10101 M
#2570000
1#
b10 K
b10110 H
13
#2580000
03
07
#2590000
0#
b0 K
13
#2600000
03
#2610000
13
#2620000
03
#2630000
13
#2640000
03
#2650000
13
#2660000
03
#2670000
13
#2680000
03
b11001001 0
b11001001 =
b11001001 C
b11001001 6
b11001001 F
17
b10110 M
#2690000
1#
b10 K
b10111 H
13
#2700000
03
07
#2710000
0#
b0 K
13
#2720000
03
#2730000
13
#2740000
03
#2750000
13
#2760000
03
#2770000
13
#2780000
03
#2790000
13
#2800000
03
b1011111 0
b1011111 =
b1011111 C
b1011111 6
b1011111 F
17
b10111 M
#2810000
1#
b10 K
b11000 H
13
#2820000
03
07
#2830000
0#
b0 K
13
#2840000
03
#2850000
13
#2860000
03
#2870000
13
#2880000
03
#2890000
13
#2900000
03
#2910000
13
#2920000
03
b1011000 0
b1011000 =
b1011000 C
b1011000 6
b1011000 F
17
b11000 M
#2930000
1#
b10 K
b11001 H
13
#2940000
03
07
#2950000
0#
b0 K
13
#2960000
03
#2970000
13
#2980000
03
#2990000
13
#3000000
03
#3010000
13
#3020000
03
#3030000
13
#3040000
03
b11001101 0
b11001101 =
b11001101 C
b11001101 6
b11001101 F
17
b11001 M
#3050000
1#
b10 K
b11010 H
13
#3060000
03
07
#3070000
0#
b0 K
13
#3080000
03
#3090000
13
#3100000
03
#3110000
13
#3120000
03
#3130000
13
#3140000
03
#3150000
13
#3160000
03
b11000 0
b11000 =
b11000 C
b11000 6
b11000 F
17
b11010 M
#3170000
1#
b10 K
b11011 H
13
#3180000
03
07
#3190000
0#
b0 K
13
#3200000
03
#3210000
13
#3220000
03
#3230000
13
#3240000
03
#3250000
13
#3260000
03
#3270000
13
#3280000
03
b1010101 0
b1010101 =
b1010101 C
b1010101 6
b1010101 F
17
b11011 M
#3290000
1#
b10 K
b11100 H
13
#3300000
03
07
#3310000
0#
b0 K
13
#3320000
03
#3330000
13
#3340000
03
#3350000
13
#3360000
03
#3370000
13
#3380000
03
#3390000
13
#3400000
03
b1001000 0
b1001000 =
b1001000 C
b1001000 6
b1001000 F
17
b11100 M
#3410000
1#
b10 K
b11101 H
13
#3420000
03
07
#3430000
0#
b0 K
13
#3440000
03
#3450000
13
#3460000
03
#3470000
13
#3480000
03
#3490000
13
#3500000
03
#3510000
13
#3520000
03
b0 0
b0 =
b0 C
b0 6
b0 F
17
b11101 M
#3530000
1#
b10 K
b11110 H
13
#3540000
03
07
#3550000
0#
b0 K
13
#3560000
03
#3570000
13
#3580000
03
#3590000
13
#3600000
03
#3610000
13
#3620000
03
#3630000
13
#3640000
03
17
b11110 M
#3650000
1#
b10 K
b11111 H
13
#3660000
03
07
#3670000
0#
b0 K
13
#3680000
03
#3690000
13
#3700000
03
#3710000
13
#3720000
03
#3730000
13
#3740000
03
#3750000
13
#3760000
03
b110100 0
b110100 =
b110100 C
b110100 6
b110100 F
17
b11111 M
#3770000
1#
b10 K
b100000 H
13
#3780000
03
07
#3790000
0#
b0 K
13
#3800000
03
#3810000
13
#3820000
03
#3830000
13
#3840000
03
#3850000
13
#3860000
03
#3870000
13
#3880000
03
b10000000 0
b10000000 =
b10000000 C
b10000000 6
b10000000 F
17
b100000 M
#3890000
1#
b10 K
b100001 H
13
#3900000
03
07
#3910000
0#
b0 K
13
#3920000
03
#3930000
13
#3940000
03
#3950000
13
#3960000
03
#3970000
13
#3980000
03
#3990000
13
#4000000
03
b0 0
b0 =
b0 C
b0 6
b0 F
17
b100001 M
#4010000
1#
b10 K
b100010 H
13
#4020000
03
07
#4030000
0#
b0 K
13
#4040000
03
#4050000
13
#4060000
03
#4070000
13
#4080000
03
#4090000
13
#4100000
03
#4110000
13
#4120000
03
17
b100010 M
#4130000
1#
b10 K
b100011 H
13
#4140000
03
07
#4150000
0#
b0 K
13
#4160000
03
#4170000
13
#4180000
03
#4190000
13
#4200000
03
#4210000
13
#4220000
03
#4230000
13
#4240000
03
b100 0
b100 =
b100 C
b100 6
b100 F
17
b100011 M
#4250000
1#
b10 K
b100100 H
13
#4260000
03
07
#4270000
0#
b0 K
13
#4280000
03
#4290000
13
#4300000
03
#4310000
13
#4320000
03
#4330000
13
#4340000
03
#4350000
13
#4360000
03
b11100110 0
b11100110 =
b11100110 C
b11100110 6
b11100110 F
17
b100100 M
#4370000
1.
b1 K
b100101 H
13
#4380000
03
07
#4390000
0.
b0 K
13
#4400000
03
#4410000
13
#4420000
03
#4430000
13
#4440000
03
#4450000
13
#4460000
03
#4470000
13
#4480000
03
b100011 0
b100011 =
b100011 C
b100011 6
b100011 F
17
b100101 M
#4490000
1.
b1 K
b100110 H
13
#4500000
03
07
#4510000
0.
b0 K
13
#4520000
03
#4530000
13
#4540000
03
#4550000
13
#4560000
03
#4570000
13
#4580000
03
#4590000
13
#4600000
03
b1101100 0
b1101100 =
b1101100 C
b1101100 6
b1101100 F
17
b100110 M
#4610000
1.
b1 K
b100111 H
13
#4620000
03
07
#4630000
0.
b0 K
13
#4640000
03
#4650000
13
#4660000
03
#4670000
13
#4680000
03
#4690000
13
#4700000
03
#4710000
13
#4720000
03
b10011010 0
b10011010 =
b10011010 C
b10011010 6
b10011010 F
17
b100111 M
#4730000
1.
b1 K
b101000 H
13
#4740000
03
07
#4750000
0.
b0 K
13
#4760000
03
#4770000
13
#4780000
03
#4790000
13
#4800000
03
#4810000
13
#4820000
03
#4830000
13
#4840000
03
b10111010 0
b10111010 =
b10111010 C
b10111010 6
b10111010 F
17
b101000 M
#4850000
1.
b1 K
b101001 H
13
#4860000
03
07
#4870000
0.
b0 K
13
#4880000
03
#4890000
13
#4900000
03
#4910000
13
#4920000
03
#4930000
13
#4940000
03
#4950000
13
#4960000
03
b10110110 0
b10110110 =
b10110110 C
b10110110 6
b10110110 F
17
b101001 M
#4970000
1.
b1 K
b101010 H
13
#4980000
03
07
#4990000
0.
b0 K
13
#5000000
03
#5010000
13
#5020000
03
#5030000
13
#5040000
03
#5050000
13
#5060000
03
#5070000
13
#5080000
03
b1001010 0
b1001010 =
b1001010 C
b1001010 6
b1001010 F
17
b101010 M
#5090000
1.
b1 K
b101011 H
13
#5100000
03
07
#5110000
0.
b0 K
13
#5120000
03
#5130000
13
#5140000
03
#5150000
13
#5160000
03
#5170000
13
#5180000
03
#5190000
13
#5200000
03
b11010 0
b11010 =
b11010 C
b11010 6
b11010 F
17
b101011 M
#5210000
1.
b1 K
b101100 H
13
#5220000
03
07
#5230000
0.
b0 K
13
#5240000
03
#5250000
13
#5260000
03
#5270000
13
#5280000
03
#5290000
13
#5300000
03
#5310000
13
#5320000
03
b11000010 0
b11000010 =
b11000010 C
b11000010 6
b11000010 F
17
b101100 M
#5330000
1.
b1 K
b101101 H
13
#5340000
03
07
#5350000
0.
b0 K
13
#5360000
03
#5370000
13
#5380000
03
#5390000
13
#5400000
03
#5410000
13
#5420000
03
#5430000
13
#5440000
03
b1000110 0
b1000110 =
b1000110 C
b1000110 6
b1000110 F
17
b101101 M
#5450000
1.
b1 K
b101110 H
13
#5460000
03
07
#5470000
0.
b0 K
13
#5480000
03
#5490000
13
#5500000
03
#5510000
13
#5520000
03
#5530000
13
#5540000
03
#5550000
13
#5560000
03
b10000001 0
b10000001 =
b10000001 C
b10000001 6
b10000001 F
17
b101110 M
#5570000
1.
b1 K
b101111 H
13
#5580000
03
07
#5590000
0.
b0 K
13
#5600000
03
#5610000
13
#5620000
03
#5630000
13
#5640000
03
#5650000
13
#5660000
03
#5670000
13
#5680000
03
b11000011 0
b11000011 =
b11000011 C
b11000011 6
b11000011 F
17
b101111 M
#5690000
1.
b1 K
b110000 H
13
#5700000
03
07
#5710000
0.
b0 K
13
#5720000
03
#5730000
13
#5740000
03
#5750000
13
#5760000
03
#5770000
13
#5780000
03
#5790000
13
#5800000
03
b11001001 0
b11001001 =
b11001001 C
b11001001 6
b11001001 F
17
b110000 M
#5810000
1.
b1 K
b110001 H
13
#5820000
03
07
#5830000
0.
b0 K
13
#5840000
03
#5850000
13
#5860000
03
#5870000
13
#5880000
03
#5890000
13
#5900000
03
#5910000
13
