Sam/sd_parser/src/side_info_2ch_v2.sv
//Try 2, just make everything explicit and more verilogy
`default_nettype none
`timescale 1ns / 1ps

module side_info_2ch(
    input wire clk,
    input wire rst,
    input wire [7:0] axiid,
    input wire axiiv,

    output logic axiov,
    output logic [8:0] main_data_begin,
    output logic [2:0] private_bits,
    output logic [1:0][3:0] scfsi,
    output logic [1:0][1:0][11:0] part2_3_length,
    output logic [1:0][1:0][8:0] big_values,
    output logic [1:0][1:0][7:0] global_gain,
    output logic [1:0][1:0][3:0] scalefac_compress,
    output logic [1:0][1:0] window_switching_flag,
    output logic [1:0][1:0][1:0] block_type,
    output logic [1:0][1:0] mixed_block_flag,
    output logic [1:0][1:0][2:0][4:0] table_select,
    output logic [1:0][1:0][2:0][2:0] subblock_gain,
    output logic [1:0][1:0][3:0] region0_count,
    output logic [1:0][1:0][3:0] region1_count,       //note: you have to make this 4 bits long to account for the default case (=12 or 13)
    output logic [1:0][1:0] preflag,
    output logic [1:0][1:0] scalefac_scale,
    output logic [1:0][1:0] count1table_select
);

    logic [5:0] side_info_byte_counter;
    logic [23:0] side_info_buffer;        //at most we need to keep track of 3 bytes at a time

    always_ff @(posedge clk) begin
      if (rst) begin
        side_info_buffer <= 0;
        side_info_byte_counter <= 0;
        axiov <= 0;
      end else begin
          if (axiiv && (side_info_byte_counter != 6'd32)) begin
            side_info_buffer <= {side_info_buffer[15:0], axiid};

            side_info_byte_counter <= side_info_byte_counter + 1;
            axiov <= 0;

          end else if (axiiv) begin
            //this is a weird case (in anticipation) where there is incoming data but
            //the module was just about to finish processing and outputting the last set.
            //shouldn't happen because the data should come in really slowly (over 18 clock cycles)
            //but just in case:
            side_info_buffer <= {side_info_buffer[15:0], axiid};
            side_info_byte_counter <= 1;    //just set it at the right thing assuming this is the first byte
            axiov <= 0;   //skip sending out the last data, it was too slow.
          end else begin
            if (side_info_byte_counter == 6'd32) begin
              axiov <= 1;
              side_info_byte_counter <= 0;
            end else begin
              axiov <= 0;
            end
          end
      end
    end

    always_ff @(posedge clk) begin
      if (rst) begin
        main_data_begin <= 0;
        private_bits <= 0;
        scfsi <= 0;
        part2_3_length <= 0;
        big_values <= 0;
        global_gain <= 0;
        scalefac_compress <= 0;
        window_switching_flag <= 0;
        block_type <= 0;
        mixed_block_flag <= 0;
        table_select <= 0;
        subblock_gain <= 0;
        region0_count <= 0;
        region1_count <= 0;
        preflag <= 0;
        scalefac_scale <= 0;
        count1table_select <= 0;
      end else begin
            case (side_info_byte_counter)
              5'd1 : begin
                  end
              5'd2 : begin
                      main_data_begin   <= side_info_buffer[15:7];
                      private_bits      <= side_info_buffer[6:4];
                      scfsi[0][0]       <= side_info_buffer[3];
                      scfsi[0][1]       <= side_info_buffer[2];
                      scfsi[0][2]       <= side_info_buffer[1];
                      scfsi[0][3]       <= side_info_buffer[0];
                  end
              5'd3 : begin
                      scfsi[1][0] <= side_info_buffer[7];
                      scfsi[1][1] <= side_info_buffer[6];
                      scfsi[1][2] <= side_info_buffer[5];
                      scfsi[1][3] <= side_info_buffer[4];
                    end
              5'd4 : begin
                      part2_3_length[0][0] <= side_info_buffer[11:0];
                    end
              5'd5 : begin

                    end
              5'd6 : begin
                      big_values[0][0] <= side_info_buffer[15:7];
                    end
              5'd7 : begin
                      global_gain[0][0] <= side_info_buffer[14:7];
                      scalefac_compress[0][0] <= side_info_buffer[6:3];
                      window_switching_flag[0][0] <= side_info_buffer[2];
                    end
              5'd8 : begin
                      if (window_switching_flag[0][0]) begin
                        block_type[0][0] <= side_info_buffer[9:8];
                        mixed_block_flag[0][0] <= side_info_buffer[7];
                        table_select[0][0][0] <= side_info_buffer[6:2];
                      end else begin
                        table_select[0][0][0] <= side_info_buffer[9:5];
                        table_select[0][0][1] <= side_info_buffer[4:0];
                      end
                    end
              5'd9 : begin
                      if (window_switching_flag[0][0]) begin
                        table_select[0][0][1] <= side_info_buffer[9:5];
                        table_select[0][0][2] <= 0;    //default value, this branch has no third region.
                        subblock_gain[0][0][0] <= side_info_buffer[4:2];
                      end else begin
                        table_select[0][0][2] <= side_info_buffer[7:3];
                      end
                    end
              5'd10 : begin
                      if (window_switching_flag[0][0]) begin
                        subblock_gain[0][0][1] <= side_info_buffer[9:7];
                        subblock_gain[0][0][2] <= side_info_buffer[6:4];
                        if ( (block_type[0][0] == 2) && (mixed_block_flag[0][0] == 0) ) begin
                          region0_count[0][0] <= 4'd8;
                          region1_count[0][0] <= 4'd12;
                        end else begin
                          region0_count[0][0] <= 4'd7;
                          region1_count[0][0] <= 4'd13;
                        end
                      end else begin
                        region0_count[0][0] <= side_info_buffer[10:7];
                        region1_count[0][0] <= side_info_buffer[6:4];
                        block_type[0][0] <= 0;
                      end

                      preflag[0][0] <= side_info_buffer[3];
                      scalefac_scale[0][0] <= side_info_buffer[2];
                      count1table_select[0][0] <= side_info_buffer[1];
                    end
              5'd11 : begin
                      //there is not enough data to make the next part2_3_length...
                    end
              5'd12 : begin
                      part2_3_length[0][1] <= side_info_buffer[16:5];
                    end
              5'd13 : begin
                      big_values[0][1] <= side_info_buffer[12:4];
                    end
              5'd14 : begin
                      global_gain[0][1] <= side_info_buffer[11:4];
                      scalefac_compress[0][1] <= side_info_buffer[3:0];
                    end
              5'd15 : begin
                      window_switching_flag[0][1] <= side_info_buffer[7];
                    end //end this early cus we need the current result for the next branch
              5'd16 : begin
                      if (window_switching_flag[0][1]) begin
                        block_type[0][1] <= side_info_buffer[14:13];
                        mixed_block_flag[0][1] <= side_info_buffer[12];
                        table_select[0][1][0] <= side_info_buffer[11:7];
                        table_select[0][1][1] <= side_info_buffer[6:2];
                        table_select[0][1][2] <= 0;    //default value
                      end else begin
                        table_select[0][1][0] <= side_info_buffer[14:10];
                        table_select[0][1][1] <= side_info_buffer[9:5];
                        table_select[0][1][2] <= side_info_buffer[4:0];
                      end
                    end
              5'd17 : begin
                      if (window_switching_flag[0][1]) begin
                        subblock_gain[0][1][0] <= side_info_buffer[9:7];
                        subblock_gain[0][1][1] <= side_info_buffer[6:4];
                        subblock_gain[0][1][2] <= side_info_buffer[3:1];
                        if ( (block_type[0][1] == 2) && (mixed_block_flag[0][1] == 0) ) begin
                          region0_count[0][1] <= 4'd8;
                          region1_count[0][1] <= 4'd12;
                        end else begin
                          region0_count[0][1] <= 4'd7;
                          region1_count[0][1] <= 4'd13;
                        end
                      end else begin
                        region0_count[0][1] <= side_info_buffer[7:4];
                        region1_count[0][1] <= side_info_buffer[3:1];
                        block_type[0][1] <= 0;   //implicit.
                        end
                    preflag[0][1] <= side_info_buffer[0];
                  end
              5'd18 : begin
                      scalefac_scale[0][1] <= side_info_buffer[7];
                      count1table_select[0][1] <= side_info_buffer[6];
                    end
              5'd19 : begin
                      part2_3_length[1][0] <= side_info_buffer[13:2];
                    end
              5'd20 : begin
                      big_values[1][0] <= side_info_buffer[9:1];
                    end
              5'd21 : begin
                      global_gain[1][0] <= side_info_buffer[8:1];
                    end
              5'd22 : begin
                      scalefac_compress[1][0] <= side_info_buffer[8:5];
                      window_switching_flag[1][0] <= side_info_buffer[4];
                    end
              5'd23 : begin
                      if (window_switching_flag[1][0]) begin
                        block_type[1][0] <= side_info_buffer[11:10];
                        mixed_block_flag[1][0] <= side_info_buffer[9];
                        table_select[1][0][0] <= side_info_buffer[8:4];
                      end else begin
                        table_select[1][0][0] <= side_info_buffer[11:7];
                        table_select[1][0][1] <= side_info_buffer[6:2];
                      end
                    end
              5'd24 : begin
                      if (window_switching_flag[1][0]) begin
                        table_select[1][0][1] <= side_info_buffer[11:7];
                        table_select[1][0][2] <= 0;     //default value
                        subblock_gain[1][0][0] <= side_info_buffer[6:4];
                        subblock_gain[1][0][1] <= side_info_buffer[3:1];
                      end else begin
                        table_select[1][0][2] <= side_info_buffer[9:5];
                        region0_count[1][0] <= side_info_buffer[4:1];
                      end
                    end
              5'd25 : begin
                      if (window_switching_flag[1][0]) begin
                        subblock_gain[1][0][2] <= side_info_buffer[8:6];
                        if ( (block_type[1][0] == 2) && (mixed_block_flag[1][0] == 0) ) begin
                          region0_count[1][0] <= 4'd8;
                          region1_count[1][0] <= 4'd12;
                        end else begin
                          region0_count[1][0] <= 4'd7;
                          region1_count[1][0] <= 4'd13;
                        end
                      end else begin
                        region1_count[1][0] <= side_info_buffer[8:6];
                        block_type[1][0] <= 0;
                      end
                      preflag[1][0] <= side_info_buffer[5];
                      scalefac_scale[1][0] <= side_info_buffer[4];
                      count1table_select[1][0] <= side_info_buffer[3];
                    end
              5'd26 : begin
                      //not enough bits
                    end
              5'd27 : begin
                      part2_3_length[1][1] <= side_info_buffer[18:7];
                    end
              5'd28 : begin
                      big_values[1][1] <= side_info_buffer[14:6];
                    end
              5'd29 : begin
                      global_gain[1][1] <= side_info_buffer[13:6];
                      scalefac_compress[1][1] <= side_info_buffer[5:2];
                      window_switching_flag[1][1] <= side_info_buffer[1];
                    end
              5'd30 : begin
                      if (window_switching_flag[1][1]) begin
                        block_type[1][1] <= side_info_buffer[8:7];
                        mixed_block_flag[1][1] <= side_info_buffer[6];
                        table_select[1][1][0] <= side_info_buffer[5:1];
                      end else begin
                        table_select[1][1][0] <= side_info_buffer[8:4];
                      end
                    end
              5'd31 : begin
                      if (window_switching_flag[1][1]) begin
                        table_select[1][1][1] <= side_info_buffer[8:4];
                        table_select[1][1][2] <= 0;   //default value
                        subblock_gain[1][1][0] <= side_info_buffer[3:1];
                      end else begin
                        table_select[1][1][1] <= side_info_buffer[11:7];
                        table_select[1][1][2] <= side_info_buffer[6:2];
                      end
                    end
              6'd32 : begin
                      if (window_switching_flag[1][1]) begin
                        subblock_gain[1][1][1] <= side_info_buffer[8:6];
                        subblock_gain[1][1][2] <= side_info_buffer[5:3];
                        if ( (block_type[1][1] == 2) && (mixed_block_flag[1][1] == 0) ) begin
                          region0_count[1][1] <= 4'd8;
                          region1_count[1][1] <= 4'd12;
                        end else begin
                          region0_count[1][1] <= 4'd7;
                          region1_count[1][1] <= 4'd13;
                        end
                      end else begin
                        region0_count[1][1] <= side_info_buffer[9:6];
                        region1_count[1][1] <= side_info_buffer[5:3];
                        block_type[1][1] <= 0;
                      end
                      preflag[1][1] <= side_info_buffer[2];
                      scalefac_scale[1][1] <= side_info_buffer[1];
                      count1table_select[1][1] <= side_info_buffer[0];   //tada
                    end
            endcase
      end

    end

endmodule

`default_nettype wire

Alex/test_builds/parser/sim/side_info_tb.sv
`default_nettype none
`timescale 1ns / 1ps

module side_info_tb;

  logic clk;
  logic rst;
  logic [7:0] axiid;
  logic axiiv;

  logic axiov;
  logic [8:0] main_data_begin;
  logic [2:0] private_bits;
  logic [1:0][3:0] scfsi;
  logic [1:0][1:0][11:0] part2_3_length;
  logic [1:0][1:0][8:0] big_values;
  logic [1:0][1:0][7:0] global_gain;
  logic [1:0][1:0][3:0] scalefac_compress;
  logic [1:0][1:0] window_switching_flag;
  logic [1:0][1:0][1:0] block_type;
  logic [1:0][1:0] mixed_block_flag;

  logic [1:0][1:0][2:0][4:0] table_select;
  logic [1:0][1:0][2:0][2:0] subblock_gain;

  logic [1:0][1:0][3:0] region0_count;
  logic [1:0][1:0][3:0] region1_count;
  logic [1:0][1:0] preflag;
  logic [1:0][1:0] scalefac_scale;
  logic [1:0][1:0] count1table_select;

  logic [255:0] sideinfo_code;

  // logic [11:0] lol_1, lol_2, lol_3, lol_4, lol_5, lol_6, lol_7, lol_8, lol_9;
  // assign lol_1 = table_select[1][1][0];
  // assign lol_2 = table_select[1][1][1];
  // assign lol_3 = table_select[1][1][2];
  // assign lol_4 = region0_count[1][1];
  // assign lol_5 = region1_count[1][1];
  // assign lol_6 = block_type[1][1];
  // assign lol_7 = preflag[1][1];
  // assign lol_8 = scalefac_scale[1][1];
  // assign lol_9 = count1table_select[1][1];

  side_info_2ch ohmygod (
    clk,
    rst,
    axiid,
    axiiv,
    axiov,

    main_data_begin,
    private_bits,
    scfsi,
    part2_3_length,
    big_values,
    global_gain,
    scalefac_compress,
    window_switching_flag,
    block_type,
    mixed_block_flag,

    table_select,
    subblock_gain,

    region0_count,
    region1_count,
    preflag,
    scalefac_scale,
    count1table_select
    );

  always begin
    #10;
    clk = !clk;     //clock cycles now happend every 20!
  end

  initial begin
    $dumpfile("sim/side_info_sim.vcd");
    $dumpvars(0, side_info_tb);
    $display("Starting Sim");

    // sideinfo_code = 256'h2082f40e6056af69000000000d20e000010ec95f58cd18554800003480000004;
    // sideinfo_code = 256'h6380f3e542d5c3291be000000d200000010f6d11542db0cd0000003480000004;
    sideinfo_code = 256'hf584f5e06ccfab4f564000000d2000000115b5a147acacfc8000003480000004;


    clk = 0;
    rst = 0;

    axiiv = 0;
    axiid = 0;    //make the inputs 0 too!
    #20;
    rst = 1;
    #20;
    rst = 0;

    //TRANSMIT DESTINATION

    for (int i = 255; i > 0; i -= 8) begin
      axiiv = 1;
      axiid = sideinfo_code[i-:8];
      #20;

      axiiv = 0;
      #40;
    end
    #200;


    sideinfo_code = 256'h6380f3e542d5c3291be000000d200000010f6d11542db0cd0000003480000004;

    //transmit new side information:
    for (int i = 255; i > 0; i -= 8) begin
      axiiv = 1;
      axiid = sideinfo_code[i-:8];
      #20;

      axiiv = 0;
      #40;
    end
    #200;


    $display("Finishing Sim");
    $finish;

  end

endmodule


`default_nettype wire

Alex/test_builds/parser/sim/side_info_sim.vcd
$date
	Sat Dec 03 12:06:07 2022
$end
$version
	Icarus Verilog
$end
$timescale
	1ps
$end
$scope module side_info_tb $end
$var wire 4 ! window_switching_flag [3:0] $end
$var wire 60 " table_select [59:0] $end
$var wire 36 # subblock_gain [35:0] $end
$var wire 8 $ scfsi [7:0] $end
$var wire 4 % scalefac_scale [3:0] $end
$var wire 16 & scalefac_compress [15:0] $end
$var wire 16 ' region1_count [15:0] $end
$var wire 16 ( region0_count [15:0] $end
$var wire 3 ) private_bits [2:0] $end
$var wire 4 * preflag [3:0] $end
$var wire 48 + part2_3_length [47:0] $end
$var wire 4 , mixed_block_flag [3:0] $end
$var wire 9 - main_data_begin [8:0] $end
$var wire 32 . global_gain [31:0] $end
$var wire 4 / count1table_select [3:0] $end
$var wire 8 0 block_type [7:0] $end
$var wire 36 1 big_values [35:0] $end
$var wire 1 2 axiov $end
$var reg 8 3 axiid [7:0] $end
$var reg 1 4 axiiv $end
$var reg 1 5 clk $end
$var reg 1 6 rst $end
$var reg 256 7 sideinfo_code [255:0] $end
$scope module ohmygod $end
$var wire 8 8 axiid [7:0] $end
$var wire 1 4 axiiv $end
$var wire 1 5 clk $end
$var wire 1 6 rst $end
$var reg 1 2 axiov $end
$var reg 36 9 big_values [35:0] $end
$var reg 8 : block_type [7:0] $end
$var reg 4 ; count1table_select [3:0] $end
$var reg 32 < global_gain [31:0] $end
$var reg 9 = main_data_begin [8:0] $end
$var reg 4 > mixed_block_flag [3:0] $end
$var reg 48 ? part2_3_length [47:0] $end
$var reg 4 @ preflag [3:0] $end
$var reg 3 A private_bits [2:0] $end
$var reg 16 B region0_count [15:0] $end
$var reg 16 C region1_count [15:0] $end
$var reg 16 D scalefac_compress [15:0] $end
$var reg 4 E scalefac_scale [3:0] $end
$var reg 8 F scfsi [7:0] $end
$var reg 24 G side_info_buffer [23:0] $end
$var reg 6 H side_info_byte_counter [5:0] $end
$var reg 36 I subblock_gain [35:0] $end
$var reg 60 J table_select [59:0] $end
$var reg 4 K window_switching_flag [3:0] $end
$upscope $end
$scope begin $ivl_for_loop0 $end
$var integer 32 L i [31:0] $end
$upscope $end
$scope begin $ivl_for_loop1 $end
$var integer 32 M i [31:0] $end
$upscope $end
$upscope $end
$enddefinitions $end
$comment Show the parameter values. $end
$dumpall
$end
#0
$dumpvars
b0 M
b0 L
bx K
bx J
bx I
bx H
bx G
bx F
bx E
bx D
bx C
bx B
bx A
bx @
bx ?
bx >
bx =
bx <
bx ;
bx :
bx 9
b0 8
b1111010110000100111101011110000001101100110011111010101101001111010101100100000000000000000000000000110100100000000000000000000000000001000101011011010110100001010001111010110010101100111111001000000000000000000000000011010010000000000000000000000000000100 7
06
05
04
b0 3
x2
bx 1
bx 0
bx /
bx .
bx -
bx ,
bx +
bx *
bx )
bx (
bx '
bx &
bx %
bx $
bx #
bx "
bx !
$end
#10000
02
15
#20000
05
16
#30000
b0 /
b0 ;
b0 %
b0 E
b0 *
b0 @
b0 '
b0 C
b0 (
b0 B
b0 #
b0 I
b0 "
b0 J
b0 ,
b0 >
b0 0
b0 :
b0 !
b0 K
b0 &
b0 D
b0 .
b0 <
b0 1
b0 9
b0 +
b0 ?
b0 $
b0 F
b0 )
b0 A
b0 -
b0 =
b0 H
b0 G
15
#40000
05
b11110101 3
b11110101 8
14
b11111111 L
06
#50000
b1 H
b11110101 G
15
#60000
05
04
#70000
15
#80000
05
#90000
15
#100000
05
b10000100 3
b10000100 8
14
b11110111 L
#110000
b10 H
b1111010110000100 G
15
#120000
05
04
#130000
b10 $
b10 F
b111101011 -
b111101011 =
15
#140000
05
#150000
15
#160000
05
b11110101 3
b11110101 8
14
b11101111 L
#170000
b11 H
b111101011000010011110101 G
15
#180000
05
04
#190000
b11110010 $
b11110010 F
15
#200000
05
#210000
15
#220000
05
b11100000 3
b11100000 8
14
b11100111 L
#230000
b100 H
b100001001111010111100000 G
15
#240000
05
04
#250000
b10111100000 +
b10111100000 ?
15
#260000
05
#270000
15
#280000
05
b1101100 3
b1101100 8
14
b11011111 L
#290000
b101 H
b111101011110000001101100 G
15
#300000
05
04
#310000
15
#320000
05
#330000
15
#340000
05
b11001111 3
b11001111 8
14
b11010111 L
#350000
b110 H
b111000000110110011001111 G
15
#360000
05
04
#370000
b11011001 1
b11011001 9
15
#380000
05
#390000
15
#400000
05
b10101011 3
b10101011 8
14
b11001111 L
#410000
b111 H
b11011001100111110101011 G
15
#420000
05
04
#430000
b101 &
b101 D
b10011111 .
b10011111 <
15
#440000
05
#450000
15
#460000
05
b1001111 3
b1001111 8
14
b11000111 L
#470000
b1000 H
b110011111010101101001111 G
15
#480000
05
04
#490000
b111111010 "
b111111010 J
15
#500000
05
#510000
15
#520000
05
b1010110 3
b1010110 8
14
b10111111 L
#530000
b1001 H
b101010110100111101010110 G
15
#540000
05
04
#550000
b10100111111010 "
b10100111111010 J
15
#560000
05
#570000
15
#580000
05
b1000000 3
b1000000 8
14
b10110111 L
#590000
b1010 H
b10011110101011001000000 G
15
#600000
05
04
#610000
b100 '
b100 C
b1100 (
b1100 B
15
#620000
05
#630000
15
#640000
05
b0 3
b0 8
14
b10101111 L
#650000
b1011 H
b10101100100000000000000 G
15
#660000
05
04
#670000
15
#680000
05
#690000
15
#700000
05
14
b10100111 L
#710000
b1100 H
b10000000000000000000000 G
15
#720000
05
04
#730000
15
#740000
05
#750000
15
#760000
05
b1101 3
b1101 8
14
b10011111 L
#770000
b1101 H
b1101 G
15
#780000
05
04
#790000
15
#800000
05
#810000
15
#820000
05
b100000 3
b100000 8
14
b10010111 L
#830000
b1110 H
b110100100000 G
15
#840000
05
04
#850000
b1101001010011111 .
b1101001010011111 <
15
#860000
05
#870000
15
#880000
05
b0 3
b0 8
14
b10001111 L
#890000
b1111 H
b11010010000000000000 G
15
#900000
05
04
#910000
15
#920000
05
#930000
15
#940000
05
14
b10000111 L
#950000
b10000 H
b1000000000000000000000 G
15
#960000
05
04
#970000
15
#980000
05
#990000
15
#1000000
05
b1 3
b1 8
14
b1111111 L
#1010000
b10001 H
b1 G
15
#1020000
05
04
#1030000
b10 *
b10 @
15
#1040000
05
#1050000
15
#1060000
05
b10101 3
b10101 8
14
b1110111 L
#1070000
b10010 H
b100010101 G
15
#1080000
05
04
#1090000
15
#1100000
05
#1110000
15
#1120000
05
b10110101 3
b10110101 8
14
b1101111 L
#1130000
b10011 H
b10001010110110101 G
15
#1140000
05
04
#1150000
b10101101101000000000000010111100000 +
b10101101101000000000000010111100000 ?
15
#1160000
05
#1170000
15
#1180000
05
b10100001 3
b10100001 8
14
b1100111 L
#1190000
b10100 H
b101011011010110100001 G
15
#1200000
05
04
#1210000
b11010000000000000011011001 1
b11010000000000000011011001 9
15
#1220000
05
#1230000
15
#1240000
05
b1000111 3
b1000111 8
14
b1011111 L
#1250000
b10101 H
b101101011010000101000111 G
15
#1260000
05
04
#1270000
b101000111101001010011111 .
b101000111101001010011111 <
15
#1280000
05
#1290000
15
#1300000
05
b10101100 3
b10101100 8
14
b1010111 L
#1310000
b10110 H
b101000010100011110101100 G
15
#1320000
05
04
#1330000
b110100000101 &
b110100000101 D
15
#1340000
05
#1350000
15
#1360000
05
14
b1001111 L
#1370000
b10111 H
b10001111010110010101100 G
15
#1380000
05
04
#1390000
b101111001000000000000000010100111111010 "
b101111001000000000000000010100111111010 J
15
#1400000
05
#1410000
15
#1420000
05
b11111100 3
b11111100 8
14
b1000111 L
#1430000
b11000 H
b101011001010110011111100 G
15
#1440000
05
04
#1450000
b111000001100 (
b111000001100 B
b1110101111001000000000000000010100111111010 "
b1110101111001000000000000000010100111111010 J
15
#1460000
05
#1470000
15
#1480000
05
b10000000 3
b10000000 8
14
b111111 L
#1490000
b11001 H
b101011001111110010000000 G
15
#1500000
05
04
#1510000
b1000000100 '
b1000000100 C
15
#1520000
05
#1530000
15
#1540000
05
b0 3
b0 8
14
b110111 L
#1550000
b11010 H
b111111001000000000000000 G
15
#1560000
05
04
#1570000
15
#1580000
05
#1590000
15
#1600000
05
14
b101111 L
#1610000
b11011 H
b100000000000000000000000 G
15
#1620000
05
04
#1630000
15
#1640000
05
#1650000
15
#1660000
05
b110100 3
b110100 8
14
b100111 L
#1670000
b11100 H
b110100 G
15
#1680000
05
04
#1690000
15
#1700000
05
#1710000
15
#1720000
05
b10000000 3
b10000000 8
14
b11111 L
#1730000
b11101 H
b11010010000000 G
15
#1740000
05
04
#1750000
b11010010101000111101001010011111 .
b11010010101000111101001010011111 <
15
#1760000
05
#1770000
15
#1780000
05
b0 3
b0 8
14
b10111 L
#1790000
b11110 H
b1101001000000000000000 G
15
#1800000
05
04
#1810000
15
#1820000
05
#1830000
15
#1840000
05
14
b1111 L
#1850000
b11111 H
b100000000000000000000000 G
15
#1860000
05
04
#1870000
15
#1880000
05
#1890000
15
#1900000
05
b100 3
b100 8
14
b111 L
#1910000
b100000 H
b100 G
15
#1920000
05
04
#1930000
b0 H
12
b1010 *
b1010 @
15
#1940000
05
#1950000
02
15
#1960000
05
b11111111111111111111111111111111 L
#1970000
15
#1980000
05
#1990000
15
#2000000
05
#2010000
15
#2020000
05
#2030000
15
#2040000
05
#2050000
15
#2060000
05
#2070000
15
#2080000
05
#2090000
15
#2100000
05
#2110000
15
#2120000
05
#2130000
15
#2140000
05
#2150000
15
#2160000
05
b1100011 3
b1100011 8
14
b11111111 M
b110001110000000111100111110010101000010110101011100001100101001000110111110000000000000000000000000110100100000000000000000000000000001000011110110110100010001010101000010110110110000110011010000000000000000000000000011010010000000000000000000000000000100 7
#2170000
b1 H
b10001100011 G
15
#2180000
05
04
#2190000
15
#2200000
05
#2210000
15
#2220000
05
b10000000 3
b10000000 8
14
b11110111 M
#2230000
b10 H
b1000110001110000000 G
15
#2240000
05
04
#2250000
b11110000 $
b11110000 F
b11000111 -
b11000111 =
15
#2260000
05
#2270000
15
#2280000
05
b11110011 3
b11110011 8
14
b11101111 M
#2290000
b11 H
b11000111000000011110011 G
15
#2300000
05
04
#2310000
15
#2320000
05
#2330000
15
#2340000
05
b11100101 3
b11100101 8
14
b11100111 M
#2350000
b100 H
b100000001111001111100101 G
15
#2360000
05
04
#2370000
b10101101101000000000000001111100101 +
b10101101101000000000000001111100101 ?
15
#2380000
05
#2390000
15
#2400000
05
b1000010 3
b1000010 8
14
b11011111 M
#2410000
b101 H
b111100111110010101000010 G
15
#2420000
05
04
#2430000
15
#2440000
05
#2450000
15
#2460000
05
b11010101 3
b11010101 8
14
b11010111 M
#2470000
b110 H
b111001010100001011010101 G
15
#2480000
05
04
#2490000
b11010000000000000010000101 1
b11010000000000000010000101 9
15
#2500000
05
#2510000
15
#2520000
05
b11000011 3
b11000011 8
14
b11001111 M
#2530000
b111 H
b10000101101010111000011 G
15
#2540000
05
04
#2550000
b110100001000 &
b110100001000 D
b11010010101000111101001010101011 .
b11010010101000111101001010101011 <
15
#2560000
05
#2570000
15
#2580000
05
b101001 3
b101001 8
14
b11000111 M
#2590000
b1000 H
b110101011100001100101001 G
15
#2600000
05
04
#2610000
b1110101111001000000000000000010100100111001 "
b1110101111001000000000000000010100100111001 J
15
#2620000
05
#2630000
15
#2640000
05
b11011 3
b11011 8
14
b10111111 M
#2650000
b1001 H
b110000110010100100011011 G
15
#2660000
05
04
#2670000
b1110101111001000000000000000000110100111001 "
b1110101111001000000000000000000110100111001 J
15
#2680000
05
#2690000
15
#2700000
05
b11100000 3
b11100000 8
14
b10110111 M
#2710000
b1010 H
b1010010001101111100000 G
15
#2720000
05
04
#2730000
b1000000110 '
b1000000110 C
b111000000111 (
b111000000111 B
15
#2740000
05
#2750000
15
#2760000
05
b0 3
b0 8
14
b10101111 M
#2770000
b1011 H
b110111110000000000000 G
15
#2780000
05
04
#2790000
15
#2800000
05
#2810000
15
#2820000
05
14
b10100111 M
#2830000
b1100 H
b111000000000000000000000 G
15
#2840000
05
04
#2850000
15
#2860000
05
#2870000
15
#2880000
05
b1101 3
b1101 8
14
b10011111 M
#2890000
b1101 H
b1101 G
15
#2900000
05
04
#2910000
15
#2920000
05
#2930000
15
#2940000
05
b100000 3
b100000 8
14
b10010111 M
#2950000
b1110 H
b110100100000 G
15
#2960000
05
04
#2970000
15
#2980000
05
#2990000
15
#3000000
05
b0 3
b0 8
14
b10001111 M
#3010000
b1111 H
b11010010000000000000 G
15
#3020000
05
04
#3030000
15
#3040000
05
#3050000
15
#3060000
05
14
b10000111 M
#3070000
b10000 H
b1000000000000000000000 G
15
#3080000
05
04
#3090000
15
#3100000
05
#3110000
15
#3120000
05
b1 3
b1 8
14
b1111111 M
#3130000
b10001 H
b1 G
15
#3140000
05
04
#3150000
15
#3160000
05
#3170000
15
#3180000
05
b1111 3
b1111 8
14
b1110111 M
#3190000
b10010 H
b100001111 G
15
#3200000
05
04
#3210000
15
#3220000
05
#3230000
15
#3240000
05
b1101101 3
b1101101 8
14
b1101111 M
#3250000
b10011 H
b10000111101101101 G
15
#3260000
05
04
#3270000
b1111011011000000000000001111100101 +
b1111011011000000000000001111100101 ?
15
#3280000
05
#3290000
15
#3300000
05
b10001 3
b10001 8
14
b1100111 M
#3310000
b10100 H
b11110110110100010001 G
15
#3320000
05
04
#3330000
b10001000000000000010000101 1
b10001000000000000010000101 9
15
#3340000
05
#3350000
15
#3360000
05
b1010100 3
b1010100 8
14
b1011111 M
#3370000
b10101 H
b11011010001000101010100 G
15
#3380000
05
04
#3390000
b11010010101010101101001010101011 .
b11010010101010101101001010101011 <
15
#3400000
05
#3410000
15
#3420000
05
b101101 3
b101101 8
14
b1010111 M
#3430000
b10110 H
b100010101010000101101 G
15
#3440000
05
04
#3450000
b100001000 &
b100001000 D
15
#3460000
05
#3470000
15
#3480000
05
b10110000 3
b10110000 8
14
b1001111 M
#3490000
b10111 H
b10101000010110110110000 G
15
#3500000
05
04
#3510000
b1110110011011000000000000000000110100111001 "
b1110110011011000000000000000000110100111001 J
15
#3520000
05
#3530000
15
#3540000
05
b11001101 3
b11001101 8
14
b1000111 M
#3550000
b11000 H
b1011011011000011001101 G
15
#3560000
05
04
#3570000
b11000000111 (
b11000000111 B
b1100110011011000000000000000000110100111001 "
b1100110011011000000000000000000110100111001 J
15
#3580000
05
#3590000
15
#3600000
05
b0 3
b0 8
14
b111111 M
#3610000
b11001 H
b101100001100110100000000 G
15
#3620000
05
04
#3630000
b10000000110 '
b10000000110 C
15
#3640000
05
#3650000
15
#3660000
05
14
b110111 M
#3670000
b11010 H
b110011010000000000000000 G
15
#3680000
05
04
#3690000
15
#3700000
05
#3710000
15
#3720000
05
14
b101111 M
#3730000
b11011 H
b0 G
15
#3740000
05
04
#3750000
15
#3760000
05
#3770000
15
#3780000
05
b110100 3
b110100 8
14
b100111 M
#3790000
b11100 H
b110100 G
15
#3800000
05
04
#3810000
15
#3820000
05
#3830000
15
#3840000
05
b10000000 3
b10000000 8
14
b11111 M
#3850000
b11101 H
b11010010000000 G
15
#3860000
05
04
#3870000
15
#3880000
05
#3890000
15
#3900000
05
b0 3
b0 8
14
b10111 M
#3910000
b11110 H
b1101001000000000000000 G
15
#3920000
05
04
#3930000
15
#3940000
05
#3950000
15
#3960000
05
14
b1111 M
#3970000
b11111 H
b100000000000000000000000 G
15
#3980000
05
04
#3990000
15
#4000000
05
#4010000
15
#4020000
05
b100 3
b100 8
14
b111 M
#4030000
b100000 H
b100 G
15
#4040000
05
04
#4050000
b0 H
12
15
#4060000
05
#4070000
02
15
#4080000
05
b11111111111111111111111111111111 M
